Workbook

Sheet 5_Resumo
A1: RESULTADO CONSOLIDADO (12 meses) — v4
A2: Serviço | B2: Receita Total | C2: Total Custos | D2: Margem R$ | E2: Margem % | F2: Preço ideal 30%
A3: Expansão | B3: 1323600 | C3: 549988 | D3: 773612 | E3: 0.58447567 | F3: 3832.669
A4: Formatação | B4: 2932500 | C4: 1469628 | D4: 1462872 | E4: 0.49884808 | F4: 43738.929
A5: Validação | B5: 306900 | C5: 330038 | D5: -23138 | E5: -0.075392636 | F5: 15209.124
A6: TOTAL | B6: 4563000 | C6: 2349654 | D6: 2213346 | E6: 0.48506377 | F6: —

Sheet 1_Base_Mensal_v4
A1: IDENTIFICAÇÃO | D1: RECEITA | G1: HORAS | L1: CUSTOS PESSOAL | Q1: CUSTOS OPERACIONAIS | Z1: RESULTADO
A2: Mês | B2: Franquia | C2: Serviço | D2: Preço Unit. | E2: Qtd | F2: Receita | G2: H_SDR | H2: H_Vend | I2: H_Cons | J2: H_GP | K2: H_Adv | L2: C_SDR | M2: C_Vend | N2: C_Cons | O2: C_CEO | P2: C_Ext | Q2: C_CAC | R2: C_Agenc | S2: C_Jur | T2: C_Contab | U2: C_GP | V2: C_Tec | W2: C_Mkt | X2: C_Tel | Y2: C_Desl | Z2: C_Trein | AA2: C_Imp | AB2: C_Com | AC2: Total Custos | AD2: Margem R$ | AE2: Margem %
A3: 2024-01 | B3: Cogni Academy | C3: Expansão | D3: 5400 | E3: 4 | F3: 21600 | G3: 151 | H3: 81 | I3: 42 | J3: 0 | K3: 0 | L3: 1036 | M3: 1036 | N3: 1250 | O3: 833 | P3: 250 | Q3: 0 | R3: - | S3: 0 | T3: 0 | U3: 0 | V3: 1093 | W3: 155 | X3: 411 | Y3: 622 | Z3: 125 | AA3: 1296 | AB3: 1080 | AC3: 10233 | AD3: 11367 | AE3: 0.52625
A4: 2024-01 | B4: Cogni Academy | C4: Formatação | D4: 69000 | E4: 1 | F4: 69000 | G4: 8 | H4: 9 | I4: 110 | J4: 0 | K4: 17 | L4: 1073 | M4: 1073 | N4: 7812 | O4: 833 | P4: 250 | Q4: 6098 | R4: 5417 | S4: 3740 | T4: 2080 | U4: 0 | V4: 1132 | W4: 161 | X4: 426 | Y4: 161 | Z4: 250 | AA4: 4140 | AB4: 3450 | AC4: 32679 | AD4: 36321 | AE4: 0.5263913
A5: 2024-01 | B5: Clínica da Cidade | C5: Expansão | D5: 10000 | E5: 4 | F5: 40000 | G5: 171 | H5: 82 | I5: 42 | J5: 0 | K5: 0 | L5: 902 | M5: 902 | N5: 1250 | O5: 833 | P5: 250 | Q5: 0 | R5: - | S5: 0 | T5: 0 | U5: 0 | V5: 952 | W5: 135 | X5: 358 | Y5: 541 | Z5: 125 | AA5: 2400 | AB5: 2000 | AC5: 12538 | AD5: 27462 | AE5: 0.68655
A6: 2024-01 | B6: Clínica da Cidade | C6: Formatação | D6: 103500 | E6: 1 | F6: 103500 | G6: 5 | H6: 10 | I6: 108 | J6: 0 | K6: 31 | L6: 1009 | M6: 1009 | N6: 7670 | O6: 833 | P6: 250 | Q6: 7098 | R6: 5938 | S6: 6820 | T6: 2080 | U6: 0 | V6: 1064 | W6: 151 | X6: 400 | Y6: 151 | Z6: 250 | AA6: 6210 | AB6: 5175 | AC6: 40170 | AD6: 63330 | AE6: 0.61188406
A7: 2024-01 | B7: Clínica da Cidade | C7: Validação | D7: 9900 | E7: 1 | F7: 9900 | G7: 0 | H7: 7 | I7: 29 | J7: 12 | K7: 0 | L7: 0 | M7: 1087 | N7: 2060 | O7: 833 | P7: 250 | Q7: 0 | R7: 5551 | S7: 0 | T7: 694 | U7: 3000 | V7: 1147 | W7: - | X7: - | Y7: - | Z7: - | AA7: 594 | AB7: 495 | AC7: =SUM(M7:AB7) -> 15711 | AD7: =F7-AC7 -> -5811 | AE7: =AD7/F7 -> -0.5869697
A8: 2024-01 | B8: Smart Nutri | C8: Expansão | D8: 10000 | E8: 4 | F8: 40000 | G8: 153 | H8: 82 | I8: 39 | J8: 0 | K8: 0 | L8: 936 | M8: 936 | N8: 1250 | O8: 833 | P8: 250 | Q8: 0 | R8: - | S8: 0 | T8: 0 | U8: 0 | V8: 987 | W8: 140 | X8: - | Y8: - | Z8: - | AA8: 2400 | AB8: 2000 | AC8: 12247 | AD8: 27753 | AE8: 0.15348485
A9: 2024-01 | B9: Smart Nutri | C9: Formatação | D9: 34500 | E9: 1 | F9: 34500 | G9: 9 | H9: 10 | I9: 103 | J9: 0 | K9: 9 | L9: 930 | M9: 930 | N9: 7315 | O9: 833 | P9: 250 | Q9: 5098 | R9: 5903 | S9: 1980 | T9: 2080 | U9: 0 | V9: 981 | W9: 140 | X9: 385 | Y9: 145 | Z9: 250 | AA9: 2070 | AB9: 1725 | AC9: 25091 | AD9: 9409 | AE9: -0.56494949
A10: 2024-01 | B10: EduKids Brasil | C10: Expansão | D10: 8000 | E10: 4 | F10: 32000 | G10: 156 | H10: 88 | I10: 41 | J10: 0 | K10: 0 | L10: 1055 | M10: 1055 | N10: 1250 | O10: 833 | P10: 250 | Q10: 0 | R10: - | S10: 0 | T10: 0 | U10: 0 | V10: 1113 | W10: 158 | X10: - | Y10: - | Z10: - | AA10: 1920 | AB10: 1600 | AC10: 12347 | AD10: 19653 | AE10: 0.16348485
A11: 2024-01 | B11: EduKids Brasil | C11: Formatação | D11: 69000 | E11: 1 | F11: 69000 | G11: 8 | H11: 9 | I11: 92 | J11: 0 | K11: 17 | L11: 1044 | M11: 1044 | N11: 6534 | O11: 833 | P11: 250 | Q11: 6098 | R11: 5445 | S11: 3740 | T11: 2080 | U11: 0 | V11: 1102 | W11: 157 | X11: 355 | Y11: 134 | Z11: 250 | AA11: 4140 | AB11: 3450 | AC11: 31294 | AD11: 37706 | AE11: -0.60666667
A12: 2024-01 | B12: EduKids Brasil | C12: Validação | D12: 9900 | E12: 2 | F12: 19800 | G12: 0 | H12: 17 | I12: 60 | J12: 43 | K12: 0 | L12: 0 | M12: 944 | N12: 3125 | O12: 833 | P12: 250 | Q12: 0 | R12: 6588 | S12: 0 | T12: 347 | U12: 1500 | V12: 996 | W12: - | X12: - | Y12: - | Z12: - | AA12: 1188 | AB12: 990 | AC12: =SUM(M12:AB12) -> 16761 | AD12: =F12-AC12 -> 3039 | AE12: =AD12/F12 -> 0.15348485
A13: 2024-02 | B13: Cogni Academy | C13: Expansão | D13: 8000 | E13: 4 | F13: 32000 | G13: 166 | H13: 82 | I13: 39 | J13: 0 | K13: 0 | L13: 917 | M13: 917 | N13: 1250 | O13: 833 | P13: 250 | Q13: 0 | R13: - | S13: 0 | T13: 0 | U13: 0 | V13: 967 | W13: 138 | X13: - | Y13: - | Z13: - | AA13: 1920 | AB13: 1600 | AC13: 11567 | AD13: 20433 | AE13: -0.56828283
A14: 2024-02 | B14: Cogni Academy | C14: Formatação | D14: 34500 | E14: 1 | F14: 34500 | G14: 8 | H14: 11 | I14: 105 | J14: 0 | K14: 8 | L14: 992 | M14: 992 | N14: 7457 | O14: 833 | P14: 250 | Q14: 5098 | R14: 5224 | S14: 1760 | T14: 2080 | U14: 0 | V14: 1047 | W14: 149 | X14: 374 | Y14: 141 | Z14: 250 | AA14: 2070 | AB14: 1725 | AC14: 25246 | AD14: 9254 | AE14: -0.56535354
A15: 2024-02 | B15: Clínica da Cidade | C15: Expansão | D15: 4500 | E15: 4 | F15: 18000 | G15: 169 | H15: 77 | I15: 38 | J15: 0 | K15: 0 | L15: 1092 | M15: 1092 | N15: 1250 | O15: 833 | P15: 250 | Q15: 0 | R15: - | S15: 0 | T15: 0 | U15: 0 | V15: 1152 | W15: 164 | X15: - | Y15: - | Z15: - | AA15: 1080 | AB15: 900 | AC15: 10378 | AD15: 7622 | AE15: 0.15262626
A16: 2024-02 | B16: Clínica da Cidade | C16: Formatação | D16: 69000 | E16: 1 | F16: 69000 | G16: 7 | H16: 11 | I16: 106 | J16: 0 | K16: 18 | L16: 881 | M16: 881 | N16: 7528 | O16: 833 | P16: 250 | Q16: 6098 | R16: 5691 | S16: 3960 | T16: 2080 | U16: 0 | V16: 929 | W16: 132 | X16: 394 | Y16: 149 | Z16: 250 | AA16: 4140 | AB16: 3450 | AC16: 31894 | AD16: 37106 | AE16: -0.6040404
A17: 2024-02 | B17: Clínica da Cidade | C17: Validação | D17: 9900 | E17: 1 | F17: 9900 | G17: 0 | H17: 8 | I17: 29 | J17: 14 | K17: 0 | L17: 0 | M17: 906 | N17: 2060 | O17: 833 | P17: 250 | Q17: 0 | R17: 5706 | S17: 0 | T17: 694 | U17: 3000 | V17: 955 | W17: - | X17: - | Y17: - | Z17: - | AA17: 594 | AB17: 495 | AC17: =SUM(M17:AB17) -> 15493 | AD17: =F17-AC17 -> -5593 | AE17: =AD17/F17 -> -0.56494949
A18: 2024-02 | B18: Smart Nutri | C18: Expansão | D18: 3000 | E18: 4 | F18: 12000 | G18: 173 | H18: 82 | I18: 40 | J18: 0 | K18: 0 | L18: 1109 | M18: 1109 | N18: 1250 | O18: 833 | P18: 250 | Q18: 0 | R18: - | S18: 0 | T18: 0 | U18: 0 | V18: 1170 | W18: 166 | X18: - | Y18: - | Z18: - | AA18: 720 | AB18: 600 | AC18: 9732 | AD18: 2268 | AE18: -0.59858586
A19: 2024-02 | B19: Smart Nutri | C19: Formatação | D19: 103500 | E19: 1 | F19: 103500 | G19: 3 | H19: 9 | I19: 96 | J19: 0 | K19: 31 | L19: 967 | M19: 967 | N19: 6818 | O19: 833 | P19: 250 | Q19: 7098 | R19: 5604 | S19: 6820 | T19: 2080 | U19: 0 | V19: 1020 | W19: 145 | X19: 368 | Y19: 139 | Z19: 250 | AA19: 6210 | AB19: 5175 | AC19: 39162 | AD19: 64338 | AE19: -0.59535354
A20: 2024-02 | B20: EduKids Brasil | C20: Expansão | D20: 4500 | E20: 4 | F20: 18000 | G20: 170 | H20: 88 | I20: 40 | J20: 0 | K20: 0 | L20: 899 | M20: 899 | N20: 1250 | O20: 833 | P20: 250 | Q20: 0 | R20: - | S20: 0 | T20: 0 | U20: 0 | V20: 948 | W20: 135 | X20: - | Y20: - | Z20: - | AA20: 1080 | AB20: 900 | AC20: 9283 | AD20: 8717 | AE20: -0.59353535
A21: 2024-02 | B21: EduKids Brasil | C21: Formatação | D21: 103500 | E21: 1 | F21: 103500 | G21: 6 | H21: 10 | I21: 103 | J21: 0 | K21: 35 | L21: 1038 | M21: 1038 | N21: 7315 | O21: 833 | P21: 250 | Q21: 7098 | R21: 5915 | S21: 7700 | T21: 2080 | U21: 0 | V21: 1095 | W21: 156 | X21: 358 | Y21: 135 | Z21: 250 | AA21: 6210 | AB21: 5175 | AC21: 40806 | AD21: 62694 | AE21: -0.59272727
A22: 2024-03 | B22: Cogni Academy | C22: Expansão | D22: 4500 | E22: 5 | F22: 22500 | G22: 176 | H22: 91 | I22: 45 | J22: 0 | K22: 0 | L22: 882 | M22: 882 | N22: 1250 | O22: 833 | P22: 250 | Q22: 0 | R22: - | S22: 0 | T22: 0 | U22: 0 | V22: 930 | W22: 132 | X22: - | Y22: - | Z22: - | AA22: 1350 | AB22: 1125 | AC22: 10089 | AD22: 12411 | AE22: 0.17116162
A23: 2024-03 | B23: Cogni Academy | C23: Formatação | D23: 34500 | E23: 1 | F23: 34500 | G23: 0 | H23: 10 | I23: 106 | J23: 0 | K23: 12 | L23: 1003 | M23: 1003 | N23: 7528 | O23: 833 | P23: 250 | Q23: 5098 | R23: 5659 | S23: 2640 | T23: 2080 | U23: 0 | V23: 1059 | W23: 151 | X23: 355 | Y23: 134 | Z23: 250 | AA23: 2070 | AB23: 1725 | AC23: 26239 | AD23: 8261 | AE23: 0.1329798
A24: 2024-03 | B24: Cogni Academy | C24: Validação | D24: 9900 | E24: 2 | F24: 19800 | G24: 0 | H24: 16 | I24: 57 | J24: 43 | K24: 0 | L24: 0 | M24: 1018 | N24: 3125 | O24: 833 | P24: 250 | Q24: 0 | R24: 6238 | S24: 0 | T24: 347 | U24: 1500 | V24: 1074 | W24: - | X24: - | Y24: - | Z24: - | AA24: 1188 | AB24: 990 | AC24: =SUM(M24:AB24) -> 16563 | AD24: =F24-AC24 -> 3237 | AE24: =AD24/F24 -> 0.16348485
A25: 2024-03 | B25: Clínica da Cidade | C25: Expansão | D25: 4500 | E25: 4 | F25: 18000 | G25: 146 | H25: 82 | I25: 41 | J25: 0 | K25: 0 | L25: 979 | M25: 979 | N25: 1250 | O25: 833 | P25: 250 | Q25: 0 | R25: - | S25: 0 | T25: 0 | U25: 0 | V25: 1032 | W25: 147 | X25: - | Y25: - | Z25: - | AA25: 1080 | AB25: 900 | AC25: 9619 | AD25: 8381 | AE25: -0.62767677
A26: 2024-03 | B26: Clínica da Cidade | C26: Formatação | D26: 69000 | E26: 1 | F26: 69000 | G26: 7 | H26: 9 | I26: 102 | J26: 0 | K26: 16 | L26: 1055 | M26: 1055 | N26: 7244 | O26: 833 | P26: 250 | Q26: 6098 | R26: 5885 | S26: 3520 | T26: 2080 | U26: 0 | V26: 1113 | W26: 158 | X26: 404 | Y26: 153 | Z26: 250 | AA26: 4140 | AB26: 3450 | AC26: 31823 | AD26: 37177 | AE26: -0.54828283
A27: 2024-03 | B27: Clínica da Cidade | C27: Validação | D27: 9900 | E27: 1 | F27: 9900 | G27: 0 | H27: 7 | I27: 33 | J27: 26 | K27: 0 | L27: 0 | M27: 924 | N27: 2344 | O27: 833 | P27: 250 | Q27: 0 | R27: 5797 | S27: 0 | T27: 694 | U27: 3000 | V27: 975 | W27: - | X27: - | Y27: - | Z27: - | AA27: 594 | AB27: 495 | AC27: =SUM(M27:AB27) -> 15906 | AD27: =F27-AC27 -> -6006 | AE27: =AD27/F27 -> -0.60666667
A28: 2024-03 | B28: Smart Nutri | C28: Expansão | D28: 5400 | E28: 5 | F28: 27000 | G28: 176 | H28: 92 | I28: 53 | J28: 0 | K28: 0 | L28: 1037 | M28: 1037 | N28: 1250 | O28: 833 | P28: 250 | Q28: 0 | R28: - | S28: 0 | T28: 0 | U28: 0 | V28: 1094 | W28: 155 | X28: - | Y28: - | Z28: - | AA28: 1620 | AB28: 1350 | AC28: 11343 | AD28: 15657 | AE28: -0.49484848
A29: 2024-03 | B29: Smart Nutri | C29: Formatação | D29: 34500 | E29: 1 | F29: 34500 | G29: 0 | H29: 11 | I29: 94 | J29: 0 | K29: 8 | L29: 978 | M29: 978 | N29: 6676 | O29: 833 | P29: 250 | Q29: 5098 | R29: 5732 | S29: 1760 | T29: 2080 | U29: 0 | V29: 1031 | W29: 147 | X29: 433 | Y29: 163 | Z29: 250 | AA29: 2070 | AB29: 1725 | AC29: 24411 | AD29: 10089 | AE29: -0.58242424
A30: 2024-03 | B30: EduKids Brasil | C30: Expansão | D30: 3000 | E30: 4 | F30: 12000 | G30: 169 | H30: 77 | I30: 42 | J30: 0 | K30: 0 | L30: 974 | M30: 974 | N30: 1250 | O30: 833 | P30: 250 | Q30: 0 | R30: - | S30: 0 | T30: 0 | U30: 0 | V30: 1027 | W30: 146 | X30: - | Y30: - | Z30: - | AA30: 720 | AB30: 600 | AC30: 9911 | AD30: 2089 | AE30: -0.5740404
A31: 2024-03 | B31: EduKids Brasil | C31: Formatação | D31: 69000 | E31: 1 | F31: 69000 | G31: 7 | H31: 9 | I31: 95 | J31: 0 | K31: 15 | L31: 1068 | M31: 1068 | N31: 6747 | O31: 833 | P31: 250 | Q31: 6098 | R31: 5442 | S31: 3300 | T31: 2080 | U31: 0 | V31: 1127 | W31: 160 | X31: 385 | Y31: 146 | Z31: 250 | AA31: 4140 | AB31: 3450 | AC31: 31155 | AD31: 37845 | AE31: -0.63808081
A32: 2024-04 | B32: Cogni Academy | C32: Expansão | D32: 5400 | E32: 4 | F32: 21600 | G32: 163 | H32: 73 | I32: 37 | J32: 0 | K32: 0 | L32: 1106 | M32: 1106 | N32: 1250 | O32: 833 | P32: 250 | Q32: 0 | R32: - | S32: 0 | T32: 0 | U32: 0 | V32: 1167 | W32: 166 | X32: - | Y32: - | Z32: - | AA32: 1296 | AB32: 1080 | AC32: 11679 | AD32: 9921 | AE32: -0.62464646
A33: 2024-04 | B33: Cogni Academy | C33: Formatação | D33: 34500 | E33: 1 | F33: 34500 | G33: 8 | H33: 10 | I33: 97 | J33: 0 | K33: 9 | L33: 1016 | M33: 1016 | N33: 6889 | O33: 833 | P33: 250 | Q33: 5098 | R33: 5228 | S33: 1980 | T33: 2080 | U33: 0 | V33: 1072 | W33: 152 | X33: 403 | Y33: 152 | Z33: 250 | AA33: 2070 | AB33: 1725 | AC33: 24986 | AD33: 9514 | AE33: 0.27576812
A34: 2024-04 | B34: Clínica da Cidade | C34: Expansão | D34: 5400 | E34: 4 | F34: 21600 | G34: 159 | H34: 87 | I34: 43 | J34: 0 | K34: 0 | L34: 911 | M34: 911 | N34: 1250 | O34: 833 | P34: 250 | Q34: 0 | R34: - | S34: 0 | T34: 0 | U34: 0 | V34: 962 | W34: 137 | X34: 362 | Y34: 547 | Z34: 125 | AA34: 1296 | AB34: 1080 | AC34: 9588 | AD34: 12012 | AE34: 0.55611111
A35: 2024-04 | B35: Clínica da Cidade | C35: Formatação | D35: 69000 | E35: 1 | F35: 69000 | G35: 7 | H35: 10 | I35: 101 | J35: 0 | K35: 16 | L35: 1029 | M35: 1029 | N35: 7173 | O35: 833 | P35: 250 | Q35: 6098 | R35: 5372 | S35: 3520 | T35: 2080 | U35: 0 | V35: 1086 | W35: 154 | X35: 409 | Y35: 154 | Z35: 250 | AA35: 4140 | AB35: 3450 | AC35: 31655 | AD35: 37345 | AE35: 0.54123188
A36: 2024-04 | B36: Smart Nutri | C36: Expansão | D36: 10000 | E36: 4 | F36: 40000 | G36: 152 | H36: 77 | I36: 40 | J36: 0 | K36: 0 | L36: 964 | M36: 964 | N36: 1250 | O36: 833 | P36: 250 | Q36: 0 | R36: - | S36: 0 | T36: 0 | U36: 0 | V36: 1017 | W36: 145 | X36: 383 | Y36: 578 | Z36: 125 | AA36: 2400 | AB36: 2000 | AC36: 12658 | AD36: 27342 | AE36: 0.68355
A37: 2024-04 | B37: Smart Nutri | C37: Formatação | D37: 103500 | E37: 1 | F37: 103500 | G37: 8 | H37: 10 | I37: 104 | J37: 0 | K37: 31 | L37: 953 | M37: 953 | N37: 7386 | O37: 833 | P37: 250 | Q37: 7098 | R37: 5573 | S37: 6820 | T37: 2080 | U37: 0 | V37: 1005 | W37: 143 | X37: 378 | Y37: 143 | Z37: 250 | AA37: 6210 | AB37: 5175 | AC37: 39677 | AD37: 63823 | AE37: 0.61664734
A38: 2024-04 | B38: EduKids Brasil | C38: Expansão | D38: 10000 | E38: 4 | F38: 40000 | G38: 172 | H38: 76 | I38: 43 | J38: 0 | K38: 0 | L38: 1104 | M38: 1104 | N38: 1250 | O38: 833 | P38: 250 | Q38: 0 | R38: - | S38: 0 | T38: 0 | U38: 0 | V38: 1164 | W38: 166 | X38: 438 | Y38: 662 | Z38: 125 | AA38: 2400 | AB38: 2000 | AC38: 13829 | AD38: 26171 | AE38: 0.654275
A39: 2024-04 | B39: EduKids Brasil | C39: Formatação | D39: 34500 | E39: 1 | F39: 34500 | G39: 4 | H39: 10 | I39: 105 | J39: 0 | K39: 11 | L39: 917 | M39: 917 | N39: 7457 | O39: 833 | P39: 250 | Q39: 5098 | R39: 5415 | S39: 2420 | T39: 2080 | U39: 0 | V39: 968 | W39: 138 | X39: 364 | Y39: 138 | Z39: 250 | AA39: 2070 | AB39: 1725 | AC39: 25625 | AD39: 8875 | AE39: 0.25724638
A40: 2024-05 | B40: Cogni Academy | C40: Expansão | D40: 3000 | E40: 4 | F40: 12000 | G40: 166 | H40: 74 | I40: 36 | J40: 0 | K40: 0 | L40: 907 | M40: 907 | N40: 1250 | O40: 833 | P40: 250 | Q40: 0 | R40: - | S40: 0 | T40: 0 | U40: 0 | V40: 957 | W40: 136 | X40: 360 | Y40: 544 | Z40: 125 | AA40: 720 | AB40: 600 | AC40: 8998 | AD40: 3002 | AE40: 0.25016667
A41: 2024-05 | B41: Cogni Academy | C41: Formatação | D41: 34500 | E41: 1 | F41: 34500 | G41: 7 | H41: 10 | I41: 110 | J41: 0 | K41: 12 | L41: 1013 | M41: 1013 | N41: 7812 | O41: 833 | P41: 250 | Q41: 5098 | R41: 5972 | S41: 2640 | T41: 2080 | U41: 0 | V41: 1068 | W41: 152 | X41: 402 | Y41: 152 | Z41: 250 | AA41: 2070 | AB41: 1725 | AC41: 26558 | AD41: 7942 | AE41: 0.2302029
A42: 2024-05 | B42: Clínica da Cidade | C42: Expansão | D42: 8000 | E42: 4 | F42: 32000 | G42: 166 | H42: 83 | I42: 39 | J42: 0 | K42: 0 | L42: 890 | M42: 890 | N42: 1250 | O42: 833 | P42: 250 | Q42: 0 | R42: - | S42: 0 | T42: 0 | U42: 0 | V42: 939 | W42: 133 | X42: 353 | Y42: 534 | Z42: 125 | AA42: 1920 | AB42: 1600 | AC42: 11354 | AD42: 20646 | AE42: 0.6451875
A43: 2024-05 | B43: Clínica da Cidade | C43: Formatação | D43: 103500 | E43: 1 | F43: 103500 | G43: 8 | H43: 11 | I43: 96 | J43: 0 | K43: 27 | L43: 1090 | M43: 1090 | N43: 6818 | O43: 833 | P43: 250 | Q43: 7098 | R43: 5183 | S43: 5940 | T43: 2080 | U43: 0 | V43: 1150 | W43: 163 | X43: 433 | Y43: 163 | Z43: 250 | AA43: 6210 | AB43: 5175 | AC43: 38743 | AD43: 64757 | AE43: 0.6256715
A44: 2024-05 | B44: Smart Nutri | C44: Expansão | D44: 8000 | E44: 4 | F44: 32000 | G44: 157 | H44: 75 | I44: 43 | J44: 0 | K44: 0 | L44: 1072 | M44: 1072 | N44: 1250 | O44: 833 | P44: 250 | Q44: 0 | R44: - | S44: 0 | T44: 0 | U44: 0 | V44: 1131 | W44: 161 | X44: 426 | Y44: 643 | Z44: 125 | AA44: 1920 | AB44: 1600 | AC44: 12813 | AD44: 19187 | AE44: 0.59959375
A45: 2024-05 | B45: Smart Nutri | C45: Formatação | D45: 69000 | E45: 1 | F45: 69000 | G45: 8 | H45: 9 | I45: 94 | J45: 0 | K45: 19 | L45: 979 | M45: 979 | N45: 6676 | O45: 833 | P45: 250 | Q45: 6098 | R45: 5786 | S45: 4180 | T45: 2080 | U45: 0 | V45: 1033 | W45: 147 | X45: 389 | Y45: 147 | Z45: 250 | AA45: 4140 | AB45: 3450 | AC45: 31631 | AD45: 37369 | AE45: 0.54157971
A46: 2024-05 | B46: EduKids Brasil | C46: Expansão | D46: 10000 | E46: 4 | F46: 40000 | G46: 159 | H46: 75 | I46: 43 | J46: 0 | K46: 0 | L46: 972 | M46: 972 | N46: 1250 | O46: 833 | P46: 250 | Q46: 0 | R46: - | S46: 0 | T46: 0 | U46: 0 | V46: 1025 | W46: 146 | X46: 386 | Y46: 583 | Z46: 125 | AA46: 2400 | AB46: 2000 | AC46: 12424 | AD46: 27576 | AE46: 0.6894
A47: 2024-05 | B47: EduKids Brasil | C47: Formatação | D47: 103500 | E47: 1 | F47: 103500 | G47: 8 | H47: 10 | I47: 99 | J47: 0 | K47: 28 | L47: 1077 | M47: 1077 | N47: 7031 | O47: 833 | P47: 250 | Q47: 7098 | R47: 5428 | S47: 6160 | T47: 2080 | U47: 0 | V47: 1136 | W47: 162 | X47: 428 | Y47: 162 | Z47: 250 | AA47: 6210 | AB47: 5175 | AC47: 39129 | AD47: 64371 | AE47: 0.62194203
A48: 2024-06 | B48: Cogni Academy | C48: Expansão | D48: 3000 | E48: 4 | F48: 12000 | G48: 148 | H48: 86 | I48: 38 | J48: 0 | K48: 0 | L48: 985 | M48: 985 | N48: 1250 | O48: 833 | P48: 250 | Q48: 0 | R48: - | S48: 0 | T48: 0 | U48: 0 | V48: 1039 | W48: 148 | X48: 391 | Y48: 591 | Z48: 125 | AA48: 720 | AB48: 600 | AC48: 8967 | AD48: 3033 | AE48: 0.25275
A49: 2024-06 | B49: Cogni Academy | C49: Formatação | D49: 69000 | E49: 1 | F49: 69000 | G49: 8 | H49: 10 | I49: 110 | J49: 0 | K49: 19 | L49: 985 | M49: 985 | N49: 7812 | O49: 833 | P49: 250 | Q49: 6098 | R49: 5404 | S49: 4180 | T49: 2080 | U49: 0 | V49: 1039 | W49: 148 | X49: 391 | Y49: 148 | Z49: 250 | AA49: 4140 | AB49: 3450 | AC49: 32789 | AD49: 36211 | AE49: 0.5247971
A50: 2024-06 | B50: Cogni Academy | C50: Validação | D50: 9900 | E50: 1 | F50: 9900 | G50: 0 | H50: 9 | I50: 32 | J50: 22 | K50: 0 | L50: 0 | M50: 927 | N50: 2273 | O50: 833 | P50: 250 | Q50: 0 | R50: 5711 | S50: 0 | T50: 694 | U50: 3000 | V50: 978 | W50: - | X50: - | Y50: - | Z50: - | AA50: 594 | AB50: 495 | AC50: =SUM(M50:AB50) -> 15755 | AD50: =F50-AC50 -> -5855 | AE50: =AD50/F50 -> -0.59141414
A51: 2024-06 | B51: Clínica da Cidade | C51: Expansão | D51: 5400 | E51: 4 | F51: 21600 | G51: 165 | H51: 77 | I51: 42 | J51: 0 | K51: 0 | L51: 1096 | M51: 1096 | N51: 1250 | O51: 833 | P51: 250 | Q51: 0 | R51: - | S51: 0 | T51: 0 | U51: 0 | V51: 1156 | W51: 164 | X51: 435 | Y51: 658 | Z51: 125 | AA51: 1296 | AB51: 1080 | AC51: 11446 | AD51: 10154 | AE51: -0.56828283
A52: 2024-06 | B52: Clínica da Cidade | C52: Formatação | D52: 69000 | E52: 1 | F52: 69000 | G52: 8 | H52: 10 | I52: 94 | J52: 0 | K52: 18 | L52: 926 | M52: 926 | N52: 6676 | O52: 833 | P52: 250 | Q52: 6098 | R52: 5874 | S52: 3960 | T52: 2080 | U52: 0 | V52: 977 | W52: 139 | X52: 368 | Y52: 139 | Z52: 250 | AA52: 4140 | AB52: 3450 | AC52: 31212 | AD52: 37788 | AE52: -0.56535354
A53: 2024-06 | B53: Smart Nutri | C53: Expansão | D53: 4500 | E53: 4 | F53: 18000 | G53: 154 | H53: 75 | I53: 42 | J53: 0 | K53: 0 | L53: 977 | M53: 977 | N53: 1250 | O53: 833 | P53: 250 | Q53: 0 | R53: - | S53: 0 | T53: 0 | U53: 0 | V53: 1031 | W53: 147 | X53: 388 | Y53: 586 | Z53: 125 | AA53: 1080 | AB53: 900 | AC53: 10411 | AD53: 7589 | AE53: 0.15262626
A54: 2024-06 | B54: Smart Nutri | C54: Formatação | D54: 34500 | E54: 1 | F54: 34500 | G54: 8 | H54: 10 | I54: 107 | J54: 0 | K54: 12 | L54: 957 | M54: 957 | N54: 7599 | O54: 833 | P54: 250 | Q54: 5098 | R54: 5763 | S54: 2640 | T54: 2080 | U54: 0 | V54: 1010 | W54: 144 | X54: 380 | Y54: 144 | Z54: 250 | AA54: 2070 | AB54: 1725 | AC54: 26137 | AD54: 8363 | AE54: -0.6040404
A55: 2024-06 | B55: Smart Nutri | C55: Validação | D55: 9900 | E55: 1 | F55: 9900 | G55: 0 | H55: 8 | I55: 32 | J55: 7 | K55: 0 | L55: 0 | M55: 1057 | N55: 2273 | O55: 833 | P55: 250 | Q55: 0 | R55: 5215 | S55: 0 | T55: 694 | U55: 3000 | V55: 1115 | W55: - | X55: - | Y55: - | Z55: - | AA55: 594 | AB55: 495 | AC55: =SUM(M55:AB55) -> 15526 | AD55: =F55-AC55 -> -5626 | AE55: =AD55/F55 -> -0.56828283
A56: 2024-06 | B56: EduKids Brasil | C56: Expansão | D56: 8000 | E56: 4 | F56: 32000 | G56: 170 | H56: 74 | I56: 36 | J56: 0 | K56: 0 | L56: 936 | M56: 936 | N56: 1250 | O56: 833 | P56: 250 | Q56: 0 | R56: - | S56: 0 | T56: 0 | U56: 0 | V56: 988 | W56: 140 | X56: 372 | Y56: 562 | Z56: 125 | AA56: 1920 | AB56: 1600 | AC56: 12230 | AD56: 19770 | AE56: -0.59858586
A57: 2024-06 | B57: EduKids Brasil | C57: Formatação | D57: 69000 | E57: 1 | F57: 69000 | G57: 6 | H57: 11 | I57: 103 | J57: 0 | K57: 19 | L57: 1027 | M57: 1027 | N57: 7315 | O57: 833 | P57: 250 | Q57: 6098 | R57: 5175 | S57: 4180 | T57: 2080 | U57: 0 | V57: 1083 | W57: 154 | X57: 408 | Y57: 154 | Z57: 250 | AA57: 4140 | AB57: 3450 | AC57: 32449 | AD57: 36551 | AE57: -0.59535354
A58: 2024-06 | B58: EduKids Brasil | C58: Validação | D58: 9900 | E58: 1 | F58: 9900 | G58: 0 | H58: 8 | I58: 33 | J58: 27 | K58: 0 | L58: 0 | M58: 972 | N58: 2344 | O58: 833 | P58: 250 | Q58: 0 | R58: 5289 | S58: 0 | T58: 694 | U58: 3000 | V58: 1026 | W58: - | X58: - | Y58: - | Z58: - | AA58: 594 | AB58: 495 | AC58: =SUM(M58:AB58) -> 15497 | AD58: =F58-AC58 -> -5597 | AE58: =AD58/F58 -> -0.56535354
A59: 2024-07 | B59: Cogni Academy | C59: Expansão | D59: 4500 | E59: 5 | F59: 22500 | G59: 70 | H59: 108 | I59: 49 | J59: 0 | K59: 0 | L59: 1076 | M59: 1076 | N59: 1250 | O59: 833 | P59: 250 | Q59: 0 | R59: - | S59: 0 | T59: 0 | U59: 0 | V59: 1135 | W59: 161 | X59: 427 | Y59: 807 | Z59: 125 | AA59: 1350 | AB59: 1125 | AC59: 10947 | AD59: 11553 | AE59: -0.59272727
A60: 2024-07 | B60: Cogni Academy | C60: Formatação | D60: 34500 | E60: 1 | F60: 34500 | G60: 106 | H60: 11 | I60: 97 | J60: 0 | K60: 11 | L60: 1087 | M60: 1087 | N60: 6889 | O60: 833 | P60: 250 | Q60: 5098 | R60: 5779 | S60: 2420 | T60: 2080 | U60: 0 | V60: 1147 | W60: 163 | X60: 431 | Y60: 163 | Z60: 250 | AA60: 2070 | AB60: 1725 | AC60: 25693 | AD60: 8807 | AE60: 0.17116162
A61: 2024-07 | B61: Cogni Academy | C61: Validação | D61: 9900 | E61: 2 | F61: 19800 | G61: 80 | H61: 17 | I61: 59 | J61: 27 | K61: 0 | L61: 0 | M61: 996 | N61: 3125 | O61: 833 | P61: 250 | Q61: 0 | R61: 6498 | S61: 0 | T61: 347 | U61: 1500 | V61: 1051 | W61: - | X61: - | Y61: - | Z61: - | AA61: 1188 | AB61: 990 | AC61: =SUM(M61:AB61) -> 16778 | AD61: =F61-AC61 -> 3022 | AE61: =AD61/F61 -> 0.15262626
A62: 2024-07 | B62: Clínica da Cidade | C62: Expansão | D62: 8000 | E62: 4 | F62: 32000 | G62: 96 | H62: 74 | I62: 38 | J62: 0 | K62: 0 | L62: 899 | M62: 899 | N62: 1250 | O62: 833 | P62: 250 | Q62: 0 | R62: - | S62: 0 | T62: 0 | U62: 0 | V62: 949 | W62: 135 | X62: 357 | Y62: 540 | Z62: 125 | AA62: 1920 | AB62: 1600 | AC62: 11216 | AD62: 20784 | AE62: -0.62131313
A63: 2024-07 | B63: Clínica da Cidade | C63: Formatação | D63: 34500 | E63: 1 | F63: 34500 | G63: 80 | H63: 11 | I63: 99 | J63: 0 | K63: 11 | L63: 959 | M63: 959 | N63: 7031 | O63: 833 | P63: 250 | Q63: 5098 | R63: 5317 | S63: 2420 | T63: 2080 | U63: 0 | V63: 1012 | W63: 144 | X63: 381 | Y63: 144 | Z63: 250 | AA63: 2070 | AB63: 1725 | AC63: 25356 | AD63: 9144 | AE63: -0.62767677
A64: 2024-07 | B64: Smart Nutri | C64: Expansão | D64: 10000 | E64: 4 | F64: 40000 | G64: 96 | H64: 81 | I64: 40 | J64: 0 | K64: 0 | L64: 1107 | M64: 1107 | N64: 1250 | O64: 833 | P64: 250 | Q64: 0 | R64: - | S64: 0 | T64: 0 | U64: 0 | V64: 1168 | W64: 166 | X64: 440 | Y64: 664 | Z64: 125 | AA64: 2400 | AB64: 2000 | AC64: 14183 | AD64: 25817 | AE64: -0.54828283
A65: 2024-07 | B65: Smart Nutri | C65: Formatação | D65: 34500 | E65: 1 | F65: 34500 | G65: 75 | H65: 11 | I65: 102 | J65: 0 | K65: 11 | L65: 952 | M65: 952 | N65: 7244 | O65: 833 | P65: 250 | Q65: 5098 | R65: 5982 | S65: 2420 | T65: 2080 | U65: 0 | V65: 1004 | W65: 143 | X65: 378 | Y65: 143 | Z65: 250 | AA65: 2070 | AB65: 1725 | AC65: 25542 | AD65: 8958 | AE65: -0.61555556
A66: 2024-07 | B66: Smart Nutri | C66: Validação | D66: 9900 | E66: 1 | F66: 9900 | G66: 101 | H66: 8 | I66: 31 | J66: 15 | K66: 0 | L66: 0 | M66: 1072 | N66: 2202 | O66: 833 | P66: 250 | Q66: 0 | R66: 5609 | S66: 0 | T66: 694 | U66: 3000 | V66: 1131 | W66: - | X66: - | Y66: - | Z66: - | AA66: 594 | AB66: 495 | AC66: =SUM(M66:AB66) -> 15880 | AD66: =F66-AC66 -> -5980 | AE66: =AD66/F66 -> -0.6040404
A67: 2024-07 | B67: EduKids Brasil | C67: Expansão | D67: 4500 | E67: 4 | F67: 18000 | G67: 91 | H67: 87 | I67: 44 | J67: 0 | K67: 0 | L67: 1072 | M67: 1072 | N67: 1250 | O67: 833 | P67: 250 | Q67: 0 | R67: - | S67: 0 | T67: 0 | U67: 0 | V67: 1130 | W67: 161 | X67: 425 | Y67: 643 | Z67: 125 | AA67: 1080 | AB67: 900 | AC67: 10871 | AD67: 7129 | AE67: -0.58242424
A68: 2024-07 | B68: EduKids Brasil | C68: Formatação | D68: 69000 | E68: 1 | F68: 69000 | G68: 85 | H68: 9 | I68: 100 | J68: 0 | K68: 19 | L68: 1098 | M68: 1098 | N68: 7102 | O68: 833 | P68: 250 | Q68: 6098 | R68: 5226 | S68: 4180 | T68: 2080 | U68: 0 | V68: 1158 | W68: 165 | X68: 436 | Y68: 165 | Z68: 250 | AA68: 4140 | AB68: 3450 | AC68: 32503 | AD68: 36497 | AE68: -0.5740404
A69: 2024-07 | B69: EduKids Brasil | C69: Validação | D69: 9900 | E69: 1 | F69: 9900 | G69: 86 | H69: 8 | I69: 30 | J69: 27 | K69: 0 | L69: 0 | M69: 924 | N69: 2131 | O69: 833 | P69: 250 | Q69: 0 | R69: 5499 | S69: 0 | T69: 694 | U69: 3000 | V69: 974 | W69: - | X69: - | Y69: - | Z69: - | AA69: 594 | AB69: 495 | AC69: =SUM(M69:AB69) -> 15394 | AD69: =F69-AC69 -> -5494 | AE69: =AD69/F69 -> -0.55494949
A70: 2024-08 | B70: Cogni Academy | C70: Expansão | D70: 8000 | E70: 5 | F70: 40000 | G70: 90 | H70: 92 | I70: 54 | J70: 0 | K70: 0 | L70: 1029 | M70: 1029 | N70: 1250 | O70: 833 | P70: 250 | Q70: 0 | R70: - | S70: 0 | T70: 0 | U70: 0 | V70: 1086 | W70: 154 | X70: 409 | Y70: 772 | Z70: 125 | AA70: 2400 | AB70: 2000 | AC70: 13084 | AD70: 26916 | AE70: -0.62464646
A71: 2024-08 | B71: Cogni Academy | C71: Formatação | D71: 34500 | E71: 1 | F71: 34500 | G71: 76 | H71: 11 | I71: 105 | J71: 0 | K71: 11 | L71: 941 | M71: 941 | N71: 7457 | O71: 833 | P71: 250 | Q71: 5098 | R71: 5324 | S71: 2420 | T71: 2080 | U71: 0 | V71: 993 | W71: 141 | X71: 374 | Y71: 141 | Z71: 250 | AA71: 2070 | AB71: 1725 | AC71: 25714 | AD71: 8786 | AE71: 0.25466667
A72: 2024-08 | B72: Cogni Academy | C72: Validação | D72: 9900 | E72: 1 | F72: 9900 | G72: 100 | H72: 9 | I72: 31 | J72: 28 | K72: 0 | L72: 0 | M72: 919 | N72: 2202 | O72: 833 | P72: 250 | Q72: 0 | R72: 5869 | S72: 0 | T72: 694 | U72: 3000 | V72: 970 | W72: - | X72: - | Y72: - | Z72: - | AA72: 594 | AB72: 495 | AC72: =SUM(M72:AB72) -> 15826 | AD72: =F72-AC72 -> -5926 | AE72: =AD72/F72 -> -0.59858586
A73: 2024-08 | B73: Clínica da Cidade | C73: Expansão | D73: 8000 | E73: 4 | F73: 32000 | G73: 92 | H73: 85 | I73: 38 | J73: 0 | K73: 0 | L73: 1106 | M73: 1106 | N73: 1250 | O73: 833 | P73: 250 | Q73: 0 | R73: - | S73: 0 | T73: 0 | U73: 0 | V73: 1167 | W73: 166 | X73: 439 | Y73: 664 | Z73: 125 | AA73: 1920 | AB73: 1600 | AC73: 12889 | AD73: 19111 | AE73: -0.59535354
A74: 2024-08 | B74: Clínica da Cidade | C74: Formatação | D74: 69000 | E74: 1 | F74: 69000 | G74: 84 | H74: 11 | I74: 102 | J74: 0 | K74: 15 | L74: 952 | M74: 952 | N74: 7244 | O74: 833 | P74: 250 | Q74: 6098 | R74: 5565 | S74: 3300 | T74: 2080 | U74: 0 | V74: 1005 | W74: 143 | X74: 378 | Y74: 143 | Z74: 250 | AA74: 4140 | AB74: 3450 | AC74: 31218 | AD74: 37782 | AE74: -0.59353535
A75: 2024-08 | B75: Clínica da Cidade | C75: Validação | D75: 9900 | E75: 1 | F75: 9900 | G75: 89 | H75: 8 | I75: 28 | J75: 16 | K75: 0 | L75: 0 | M75: 1008 | N75: 1989 | O75: 833 | P75: 250 | Q75: 0 | R75: 5868 | S75: 0 | T75: 694 | U75: 3000 | V75: 1063 | W75: - | X75: - | Y75: - | Z75: - | AA75: 594 | AB75: 495 | AC75: =SUM(M75:AB75) -> 15794 | AD75: =F75-AC75 -> -5894 | AE75: =AD75/F75 -> -0.59535354
A76: 2024-08 | B76: Smart Nutri | C76: Expansão | D76: 8000 | E76: 4 | F76: 32000 | G76: 87 | H76: 79 | I76: 37 | J76: 0 | K76: 0 | L76: 984 | M76: 984 | N76: 1250 | O76: 833 | P76: 250 | Q76: 0 | R76: - | S76: 0 | T76: 0 | U76: 0 | V76: 1038 | W76: 148 | X76: 391 | Y76: 590 | Z76: 125 | AA76: 1920 | AB76: 1600 | AC76: 11357 | AD76: 20643 | AE76: 0.17116162
A77: 2024-08 | B77: Smart Nutri | C77: Formatação | D77: 69000 | E77: 1 | F77: 69000 | G77: 70 | H77: 11 | I77: 107 | J77: 0 | K77: 17 | L77: 1005 | M77: 1005 | N77: 7599 | O77: 833 | P77: 250 | Q77: 6098 | R77: 5311 | S77: 3740 | T77: 2080 | U77: 0 | V77: 1061 | W77: 151 | X77: 399 | Y77: 151 | Z77: 250 | AA77: 4140 | AB77: 3450 | AC77: 32212 | AD77: 36788 | AE77: 0.1329798
A78: 2024-08 | B78: EduKids Brasil | C78: Expansão | D78: 5400 | E78: 5 | F78: 27000 | G78: 106 | H78: 95 | I78: 54 | J78: 0 | K78: 0 | L78: 1078 | M78: 1078 | N78: 1250 | O78: 833 | P78: 250 | Q78: 0 | R78: - | S78: 0 | T78: 0 | U78: 0 | V78: 1137 | W78: 162 | X78: 428 | Y78: 809 | Z78: 125 | AA78: 1620 | AB78: 1350 | AC78: 11649 | AD78: 15351 | AE78: -0.62131313
A79: 2024-08 | B79: EduKids Brasil | C79: Formatação | D79: 69000 | E79: 1 | F79: 69000 | G79: 95 | H79: 10 | I79: 98 | J79: 0 | K79: 17 | L79: 988 | M79: 988 | N79: 6960 | O79: 833 | P79: 250 | Q79: 6098 | R79: 5756 | S79: 3740 | T79: 2080 | U79: 0 | V79: 1043 | W79: 148 | X79: 392 | Y79: 148 | Z79: 250 | AA79: 4140 | AB79: 3450 | AC79: 31508 | AD79: 37492 | AE79: -0.62767677
A80: 2024-09 | B80: Cogni Academy | C80: Expansão | D80: 4500 | E80: 4 | F80: 18000 | G80: 81 | H80: 72 | I80: 38 | J80: 0 | K80: 0 | L80: 994 | M80: 994 | N80: 1250 | O80: 833 | P80: 250 | Q80: 0 | R80: - | S80: 0 | T80: 0 | U80: 0 | V80: 1049 | W80: 149 | X80: 395 | Y80: 597 | Z80: 125 | AA80: 1080 | AB80: 900 | AC80: 10213 | AD80: 7787 | AE80: -0.54828283
A81: 2024-09 | B81: Cogni Academy | C81: Formatação | D81: 69000 | E81: 1 | F81: 69000 | G81: 78 | H81: 10 | I81: 98 | J81: 0 | K81: 20 | L81: 938 | M81: 938 | N81: 6960 | O81: 833 | P81: 250 | Q81: 6098 | R81: 5474 | S81: 4400 | T81: 2080 | U81: 0 | V81: 990 | W81: 141 | X81: 373 | Y81: 141 | Z81: 250 | AA81: 4140 | AB81: 3450 | AC81: 31982 | AD81: 37018 | AE81: -0.61555556
A82: 2024-09 | B82: Cogni Academy | C82: Validação | D82: 9900 | E82: 1 | F82: 9900 | G82: 98 | H82: 8 | I82: 29 | J82: 23 | K82: 0 | L82: 0 | M82: 1012 | N82: 2060 | O82: 833 | P82: 250 | Q82: 0 | R82: 5770 | S82: 0 | T82: 694 | U82: 3000 | V82: 1068 | W82: - | X82: - | Y82: - | Z82: - | AA82: 594 | AB82: 495 | AC82: =SUM(M82:AB82) -> 15776 | AD82: =F82-AC82 -> -5876 | AE82: =AD82/F82 -> -0.59353535
A83: 2024-09 | B83: Clínica da Cidade | C83: Expansão | D83: 3000 | E83: 4 | F83: 12000 | G83: 72 | H83: 75 | I83: 42 | J83: 0 | K83: 0 | L83: 1058 | M83: 1058 | N83: 1250 | O83: 833 | P83: 250 | Q83: 0 | R83: - | S83: 0 | T83: 0 | U83: 0 | V83: 1116 | W83: 159 | X83: 420 | Y83: 635 | Z83: 125 | AA83: 720 | AB83: 600 | AC83: 9721 | AD83: 2279 | AE83: -0.58242424
A84: 2024-09 | B84: Clínica da Cidade | C84: Formatação | D84: 69000 | E84: 1 | F84: 69000 | G84: 104 | H84: 11 | I84: 108 | J84: 0 | K84: 16 | L84: 1022 | M84: 1022 | N84: 7670 | O84: 833 | P84: 250 | Q84: 6098 | R84: 5918 | S84: 3520 | T84: 2080 | U84: 0 | V84: 1078 | W84: 153 | X84: 406 | Y84: 153 | Z84: 250 | AA84: 4140 | AB84: 3450 | AC84: 32125 | AD84: 36875 | AE84: -0.5740404
A85: 2024-09 | B85: Clínica da Cidade | C85: Validação | D85: 9900 | E85: 1 | F85: 9900 | G85: 85 | H85: 7 | I85: 28 | J85: 6 | K85: 0 | L85: 0 | M85: 967 | N85: 1989 | O85: 833 | P85: 250 | Q85: 0 | R85: 5926 | S85: 0 | T85: 694 | U85: 3000 | V85: 1020 | W85: - | X85: - | Y85: - | Z85: - | AA85: 594 | AB85: 495 | AC85: =SUM(M85:AB85) -> 15768 | AD85: =F85-AC85 -> -5868 | AE85: =AD85/F85 -> -0.59272727
A86: 2024-09 | B86: Smart Nutri | C86: Expansão | D86: 5400 | E86: 4 | F86: 21600 | G86: 91 | H86: 74 | I86: 36 | J86: 0 | K86: 0 | L86: 1107 | M86: 1107 | N86: 1250 | O86: 833 | P86: 250 | Q86: 0 | R86: - | S86: 0 | T86: 0 | U86: 0 | V86: 1167 | W86: 166 | X86: 439 | Y86: 664 | Z86: 125 | AA86: 1296 | AB86: 1080 | AC86: 11063 | AD86: 10537 | AE86: -0.62464646
A87: 2024-09 | B87: Smart Nutri | C87: Formatação | D87: 34500 | E87: 1 | F87: 34500 | G87: 84 | H87: 10 | I87: 108 | J87: 0 | K87: 8 | L87: 995 | M87: 995 | N87: 7670 | O87: 833 | P87: 250 | Q87: 5098 | R87: 5149 | S87: 1760 | T87: 2080 | U87: 0 | V87: 1050 | W87: 149 | X87: 395 | Y87: 149 | Z87: 250 | AA87: 2070 | AB87: 1725 | AC87: 25469 | AD87: 9031 | AE87: 0.26176812
A88: 2024-09 | B88: EduKids Brasil | C88: Expansão | D88: 5400 | E88: 5 | F88: 27000 | G88: 92 | H88: 104 | I88: 47 | J88: 0 | K88: 0 | L88: 896 | M88: 896 | N88: 1250 | O88: 833 | P88: 250 | Q88: 0 | R88: - | S88: 0 | T88: 0 | U88: 0 | V88: 945 | W88: 134 | X88: 356 | Y88: 672 | Z88: 125 | AA88: 1620 | AB88: 1350 | AC88: 11312 | AD88: 15688 | AE88: 0.58103704
A89: 2024-09 | B89: EduKids Brasil | C89: Formatação | D89: 34500 | E89: 1 | F89: 34500 | G89: 89 | H89: 10 | I89: 99 | J89: 0 | K89: 10 | L89: 1108 | M89: 1108 | N89: 7031 | O89: 833 | P89: 250 | Q89: 5098 | R89: 5446 | S89: 2200 | T89: 2080 | U89: 0 | V89: 1169 | W89: 166 | X89: 440 | Y89: 166 | Z89: 250 | AA89: 2070 | AB89: 1725 | AC89: 25694 | AD89: 8806 | AE89: 0.25524638
A90: 2024-09 | B90: EduKids Brasil | C90: Validação | D90: 9900 | E90: 2 | F90: 19800 | G90: 87 | H90: 17 | I90: 59 | J90: 39 | K90: 0 | L90: 0 | M90: 1028 | N90: 3125 | O90: 833 | P90: 250 | Q90: 0 | R90: 6065 | S90: 0 | T90: 347 | U90: 1500 | V90: 1085 | W90: - | X90: - | Y90: - | Z90: - | AA90: 1188 | AB90: 990 | AC90: =SUM(M90:AB90) -> 16411 | AD90: =F90-AC90 -> 3389 | AE90: =AD90/F90 -> 0.17116162
A91: 2024-10 | B91: Cogni Academy | C91: Expansão | D91: 8000 | E91: 5 | F91: 40000 | G91: 93 | H91: 107 | I91: 46 | J91: 0 | K91: 0 | L91: 888 | M91: 888 | N91: 1250 | O91: 833 | P91: 250 | Q91: 0 | R91: - | S91: 0 | T91: 0 | U91: 0 | V91: 937 | W91: 133 | X91: 352 | Y91: 666 | Z91: 125 | AA91: 2400 | AB91: 2000 | AC91: 11921 | AD91: 28079 | AE91: 0.1329798
A92: 2024-10 | B92: Cogni Academy | C92: Formatação | D92: 69000 | E92: 1 | F92: 69000 | G92: 83 | H92: 11 | I92: 95 | J92: 0 | K92: 16 | L92: 943 | M92: 943 | N92: 6747 | O92: 833 | P92: 250 | Q92: 6098 | R92: 5320 | S92: 3520 | T92: 2080 | U92: 0 | V92: 995 | W92: 142 | X92: 375 | Y92: 142 | Z92: 250 | AA92: 4140 | AB92: 3450 | AC92: 30908 | AD92: 38092 | AE92: -0.62131313
A93: 2024-10 | B93: Clínica da Cidade | C93: Expansão | D93: 10000 | E93: 5 | F93: 50000 | G93: 80 | H93: 93 | I93: 46 | J93: 0 | K93: 0 | L93: 934 | M93: 934 | N93: 1250 | O93: 833 | P93: 250 | Q93: 0 | R93: - | S93: 0 | T93: 0 | U93: 0 | V93: 985 | W93: 140 | X93: 371 | Y93: 700 | Z93: 125 | AA93: 3000 | AB93: 2500 | AC93: 14066 | AD93: 35934 | AE93: -0.62767677
A94: 2024-10 | B94: Clínica da Cidade | C94: Formatação | D94: 69000 | E94: 1 | F94: 69000 | G94: 96 | H94: 10 | I94: 100 | J94: 0 | K94: 17 | L94: 1023 | M94: 1023 | N94: 7102 | O94: 833 | P94: 250 | Q94: 6098 | R94: 5750 | S94: 3740 | T94: 2080 | U94: 0 | V94: 1079 | W94: 153 | X94: 406 | Y94: 153 | Z94: 250 | AA94: 4140 | AB94: 3450 | AC94: 31780 | AD94: 37220 | AE94: -0.54828283
A95: 2024-10 | B95: Clínica da Cidade | C95: Validação | D95: 9900 | E95: 2 | F95: 19800 | G95: 78 | H95: 16 | I95: 63 | J95: 54 | K95: 0 | L95: 0 | M95: 977 | N95: 3125 | O95: 833 | P95: 250 | Q95: 0 | R95: 6927 | S95: 0 | T95: 347 | U95: 1500 | V95: 1030 | W95: - | X95: - | Y95: - | Z95: - | AA95: 1188 | AB95: 990 | AC95: =SUM(M95:AB95) -> 17167 | AD95: =F95-AC95 -> 2633 | AE95: =AD95/F95 -> 0.1329798
A96: 2024-10 | B96: Smart Nutri | C96: Expansão | D96: 10000 | E96: 4 | F96: 40000 | G96: 98 | H96: 83 | I96: 43 | J96: 0 | K96: 0 | L96: 1025 | M96: 1025 | N96: 1250 | O96: 833 | P96: 250 | Q96: 0 | R96: - | S96: 0 | T96: 0 | U96: 0 | V96: 1081 | W96: 154 | X96: 407 | Y96: 615 | Z96: 125 | AA96: 2400 | AB96: 2000 | AC96: 13092 | AD96: 26908 | AE96: -0.49484848
A97: 2024-10 | B97: Smart Nutri | C97: Formatação | D97: 69000 | E97: 1 | F97: 69000 | G97: 94 | H97: 10 | I97: 106 | J97: 0 | K97: 16 | L97: 885 | M97: 885 | N97: 7528 | O97: 833 | P97: 250 | Q97: 6098 | R97: 5254 | S97: 3520 | T97: 2080 | U97: 0 | V97: 934 | W97: 133 | X97: 351 | Y97: 133 | Z97: 250 | AA97: 4140 | AB97: 3450 | AC97: 31470 | AD97: 37530 | AE97: -0.58242424
A98: 2024-10 | B98: EduKids Brasil | C98: Expansão | D98: 8000 | E98: 4 | F98: 32000 | G98: 82 | H98: 88 | I98: 39 | J98: 0 | K98: 0 | L98: 1005 | M98: 1005 | N98: 1250 | O98: 833 | P98: 250 | Q98: 0 | R98: - | S98: 0 | T98: 0 | U98: 0 | V98: 1060 | W98: 151 | X98: 399 | Y98: 603 | Z98: 125 | AA98: 1920 | AB98: 1600 | AC98: 12432 | AD98: 19568 | AE98: -0.5740404
A99: 2024-10 | B99: EduKids Brasil | C99: Formatação | D99: 34500 | E99: 1 | F99: 34500 | G99: 86 | H99: 10 | I99: 93 | J99: 0 | K99: 9 | L99: 1113 | M99: 1113 | N99: 6605 | O99: 833 | P99: 250 | Q99: 5098 | R99: 5939 | S99: 1980 | T99: 2080 | U99: 0 | V99: 1174 | W99: 167 | X99: 442 | Y99: 167 | Z99: 250 | AA99: 2070 | AB99: 1725 | AC99: 25067 | AD99: 9433 | AE99: -0.63808081
A100: 2024-10 | B100: EduKids Brasil | C100: Validação | D100: 9900 | E100: 1 | F100: 9900 | G100: 90 | H100: 8 | I100: 33 | J100: 6 | K100: 0 | L100: 0 | M100: 979 | N100: 2344 | O100: 833 | P100: 250 | Q100: 0 | R100: 5829 | S100: 0 | T100: 694 | U100: 3000 | V100: 1033 | W100: - | X100: - | Y100: - | Z100: - | AA100: 594 | AB100: 495 | AC100: =SUM(M100:AB100) -> 16051 | AD100: =F100-AC100 -> -6151 | AE100: =AD100/F100 -> -0.62131313
...

Sheet 2_Premissas_v4
A1: PREMISSAS VIGENTES — v4
A2: Parâmetro | B2: Valor
A3: Horas úteis/mês | B3: 176
A4: Salário Consultor PJ (Format.+Valid.) | B4: 12500
A5: % horas consultor → Formatação | B5: 75%
A6: % horas consultor → Validação | B6: 25%
A7: Custo/hora consultor | B7: R$ 71,02/h
A8: Custo/hora advogado PJ | B8: R$ 220,00/h
A9: Salário GP (fixo mensal, só Valid.) | B9: R$ 3.000
A10: Contabilidade mensal (Format.+Valid.) | B10: R$ 2.774
A11: Contabilidade → Formatação (75%) | B11: R$ 2.080/mês
A12: Contabilidade → Validação (25%) | B12: R$ 694/mês
A14: CAC FORMATAÇÃO POR TIER
A15: Tier R$34.500 | B15: R$ 5.098/contrato
A16: Tier R$69.000 | B16: R$ 6.098/contrato
A17: Tier R$103.500 | B17: R$ 7.098/contrato
A19: HORAS ADVOGADO POR TIER (Formatação)
A20: Tier R$34.500 | B20: 8 a 12h/contrato
A21: Tier R$69.000 | B21: 15 a 20h/contrato
A22: Tier R$103.500 | B22: 25 a 35h/contrato
A24: VALIDAÇÃO — AJUSTES v4
A25: Custo SDR | B25: R$ 0 (sem SDR nessa fase)
A26: Horas GP por contrato | B26: 5h a 30h (driver de complexidade)
A27: GP entra na regressão? | B27: Não — custo fixo rateado
A28: Alíquota imposto | B28: 6,0%
A29: Comissão vendas | B29: 5,0%

Sheet 3_Resultados_v4
A1: RESULTADOS DOS MODELOS DE REGRESSÃO — v4
A2: Serviço | B2: R² | C2: R²aj | D2: F (p-val) | E2: MAE (R$) | F2: Custo/contrato | G2: Breakeven | H2: Preço ideal 30%
A3: Expansão | B3: 0.098 | C3: 0.037 | D3: 1.6 (p=0.2033) | E3: R$1,071 | F3: R$2,683 | G3: R$2,683 | H3: R$3,833
A4: Formatação | B4: 0.951 | C4: 0.947 | D4: 282.4 (p=0.0000) | E4: R$889 | F4: R$30,617 | G4: R$30,617 | H4: R$43,739
A5: Validação | B5: 0.208 | C5: 0.100 | D5: 1.9 (p=0.1550) | E5: R$437 | F5: R$10,646 | G5: R$10,646 | H5: R$15,209
A6: COEFICIENTES β — MODELO 1 (Y = Custo Total)
A7: Serviço | B7: Variável | C7: β | D7: p-valor | E7: Sig. | F7: Elasticidade
A8: Expansão | B8: const | C8: 7354.25 | D8: 0.046 | E8: ** | F8: —
B9: Qtd_Contratos | C9: 240.84 | D9: 0.758 | E9: ns | F9: 0.09
B10: H_Total | C10: 12.48 | D10: 0.647 | E10: ns | F10: 0.227
B11: Num_Mes | C11: 72.2 | D11: 0.245 | E11: ns | F11: 0.041
A13: Formatação | B13: const | C13: 7029.42 | D13: 0 | E13: *** | F13: —
B14: Qtd_Contratos | C14: 7029.42 | D14: 0 | E14: *** | F14: 0.23
B15: H_Total | C15: 45.57 | D15: 0.061 | E15: * | F15: 0.159
B16: H_Advogado | C16: 686.23 | D16: 0 | E16: *** | F16: 0.37
B17: Num_Mes | C17: 56.02 | D17: 0.244 | E17: ns | F17: 0.012
A19: Validação | B19: const | C19: 11551.5 | D19: 0 | E19: *** | F19: —
B20: Qtd_Contratos | C20: -498.03 | D20: 0.793 | E20: ns | F20: -0.047
B21: H_Total | C21: 40.98 | D21: 0.524 | E21: ns | F21: 0.117
B22: Num_Mes | C22: 32.24 | D22: 0.372 | E22: ns | F22: 0.02

Sheet Planilha3
A1: Mês | B1: Franquia | C1: Serviço | D1: Preço Unit. | E1: Qtd | F1: Receita | G1: H_SDR | H1: H_Vend | I1: H_Cons | J1: H_GP | K1: H_Adv | L1: C_SDR | M1: C_Vend | N1: C_Cons | O1: C_CEO | P1: C_Ext | Q1: C_CAC | R1: C_Agenc | S1: C_Jur | T1: C_Contab | U1: C_GP | V1: C_Tec | W1: C_Mkt | X1: C_Tel | Y1: C_Desl | Z1: C_Trein | AA1: C_Imp | AB1: C_Com | AC1: Total Custos | AD1: Margem R$ | AE1: Margem %
A2: 2024-01 | B2: Cogni Academy | C2: Expansão | D2: 5400 | E2: 4 | F2: 21600 | G2: 151 | H2: 81 | I2: 42 | J2: 0 | K2: 0 | L2: 1036 | M2: 1036 | N2: 1250 | O2: 833 | P2: 250 | Q2: 0 | R2: - | S2: 0 | T2: 0 | U2: 0 | V2: 1093 | W2: 155 | X2: 411 | Y2: 622 | Z2: 125 | AA2: 1296 | AB2: 1080 | AC2: 10233 | AD2: 11367 | AE2: 0.52625
A3: 2024-01 | B3: Clínica da Cidade | C3: Expansão | D3: 10000 | E3: 4 | F3: 40000 | G3: 171 | H3: 82 | I3: 42 | J3: 0 | K3: 0 | L3: 902 | M3: 902 | N3: 1250 | O3: 833 | P3: 250 | Q3: 0 | R3: - | S3: 0 | T3: 0 | U3: 0 | V3: 952 | W3: 135 | X3: 358 | Y3: 541 | Z3: 125 | AA3: 2400 | AB3: 2000 | AC3: 12538 | AD3: 27462 | AE3: 0.68655
A4: 2024-01 | B4: Smart Nutri | C4: Expansão | D4: 10000 | E4: 4 | F4: 40000 | G4: 153 | H4: 82 | I4: 39 | J4: 0 | K4: 0 | L4: 936 | M4: 936 | N4: 1250 | O4: 833 | P4: 250 | Q4: 0 | R4: - | S4: 0 | T4: 0 | U4: 0 | V4: 987 | W4: 140 | X4: 372 | Y4: 562 | Z4: 125 | AA4: 2400 | AB4: 2000 | AC4: 12247 | AD4: 27753 | AE4: 0.15348485
A5: 2024-01 | B5: EduKids Brasil | C5: Expansão | D5: 8000 | E5: 4 | F5: 32000 | G5: 156 | H5: 88 | I5: 41 | J5: 0 | K5: 0 | L5: 1055 | M5: 1055 | N5: 1250 | O5: 833 | P5: 250 | Q5: 0 | R5: - | S5: 0 | T5: 0 | U5: 0 | V5: 1113 | W5: 158 | X5: 419 | Y5: 633 | Z5: 125 | AA5: 1920 | AB5: 1600 | AC5: 12347 | AD5: 19653 | AE5: 0.16348485
A6: 2024-02 | B6: Cogni Academy | C6: Expansão | D6: 8000 | E6: 4 | F6: 32000 | G6: 166 | H6: 82 | I6: 39 | J6: 0 | K6: 0 | L6: 917 | M6: 917 | N6: 1250 | O6: 833 | P6: 250 | Q6: 0 | R6: - | S6: 0 | T6: 0 | U6: 0 | V6: 967 | W6: 138 | X6: 364 | Y6: 550 | Z6: 125 | AA6: 1920 | AB6: 1600 | AC6: 11567 | AD6: 20433 | AE6: -0.56828283
A7: 2024-02 | B7: Clínica da Cidade | C7: Expansão | D7: 4500 | E7: 4 | F7: 18000 | G7: 169 | H7: 77 | I7: 38 | J7: 0 | K7: 0 | L7: 1092 | M7: 1092 | N7: 1250 | O7: 833 | P7: 250 | Q7: 0 | R7: - | S7: 0 | T7: 0 | U7: 0 | V7: 1152 | W7: 164 | X7: 434 | Y7: 655 | Z7: 125 | AA7: 1080 | AB7: 900 | AC7: 10378 | AD7: 7622 | AE7: 0.15262626
A8: 2024-02 | B8: Smart Nutri | C8: Expansão | D8: 3000 | E8: 4 | F8: 12000 | G8: 173 | H8: 82 | I8: 40 | J8: 0 | K8: 0 | L8: 1109 | M8: 1109 | N8: 1250 | O8: 833 | P8: 250 | Q8: 0 | R8: - | S8: 0 | T8: 0 | U8: 0 | V8: 1170 | W8: 166 | X8: 440 | Y8: 665 | Z8: 125 | AA8: 720 | AB8: 600 | AC8: 9732 | AD8: 2268 | AE8: -0.59858586
A9: 2024-02 | B9: EduKids Brasil | C9: Expansão | D9: 4500 | E9: 4 | F9: 18000 | G9: 170 | H9: 88 | I9: 40 | J9: 0 | K9: 0 | L9: 899 | M9: 899 | N9: 1250 | O9: 833 | P9: 250 | Q9: 0 | R9: - | S9: 0 | T9: 0 | U9: 0 | V9: 948 | W9: 135 | X9: 357 | Y9: 539 | Z9: 125 | AA9: 1080 | AB9: 900 | AC9: 9283 | AD9: 8717 | AE9: -0.59353535
A10: 2024-03 | B10: Cogni Academy | C10: Expansão | D10: 4500 | E10: 5 | F10: 22500 | G10: 176 | H10: 91 | I10: 45 | J10: 0 | K10: 0 | L10: 882 | M10: 882 | N10: 1250 | O10: 833 | P10: 250 | Q10: 0 | R10: - | S10: 0 | T10: 0 | U10: 0 | V10: 930 | W10: 132 | X10: 350 | Y10: 661 | Z10: 125 | AA10: 1350 | AB10: 1125 | AC10: 10089 | AD10: 12411 | AE10: 0.17116162
A11: 2024-03 | B11: Clínica da Cidade | C11: Expansão | D11: 4500 | E11: 4 | F11: 18000 | G11: 146 | H11: 82 | I11: 41 | J11: 0 | K11: 0 | L11: 979 | M11: 979 | N11: 1250 | O11: 833 | P11: 250 | Q11: 0 | R11: - | S11: 0 | T11: 0 | U11: 0 | V11: 1032 | W11: 147 | X11: 389 | Y11: 587 | Z11: 125 | AA11: 1080 | AB11: 900 | AC11: 9619 | AD11: 8381 | AE11: -0.62767677
A12: 2024-03 | B12: Smart Nutri | C12: Expansão | D12: 5400 | E12: 5 | F12: 27000 | G12: 176 | H12: 92 | I12: 53 | J12: 0 | K12: 0 | L12: 1037 | M12: 1037 | N12: 1250 | O12: 833 | P12: 250 | Q12: 0 | R12: - | S12: 0 | T12: 0 | U12: 0 | V12: 1094 | W12: 155 | X12: 411 | Y12: 777 | Z12: 125 | AA12: 1620 | AB12: 1350 | AC12: 11343 | AD12: 15657 | AE12: -0.49484848
A13: 2024-03 | B13: EduKids Brasil | C13: Expansão | D13: 3000 | E13: 4 | F13: 12000 | G13: 169 | H13: 77 | I13: 42 | J13: 0 | K13: 0 | L13: 974 | M13: 974 | N13: 1250 | O13: 833 | P13: 250 | Q13: 0 | R13: - | S13: 0 | T13: 0 | U13: 0 | V13: 1027 | W13: 146 | X13: 387 | Y13: 584 | Z13: 125 | AA13: 720 | AB13: 600 | AC13: 9911 | AD13: 2089 | AE13: -0.5740404
... A49: 2024-12 | B49: EduKids Brasil | C49: Expansão | D49: 4500 | E49: 4 | F49: 18000 | G49: 163 | H49: 78 | I49: 41 | J49: 0 | K49: 0 | L49: 949 | M49: 949 | N49: 1250 | O49: 833 | P49: 250 | Q49: 0 | R49: - | S49: 0 | T49: 0 | U49: 0 | V49: 1001 | W49: 142 | X49: 377 | Y49: 569 | Z49: 125 | AA49: 1080 | AB49: 900 | AC49: 10257 | AD49: 7743 | AE49: -0.62464646

Sheet Planilha1
A1: Mês | B1: Franquia | C1: Serviço | D1: Preço Unit. | E1: Qtd | F1: Receita | G1: H_SDR | H1: H_Vend | I1: H_Cons | J1: H_GP | K1: H_Adv | L1: C_SDR | M1: C_Vend | N1: C_Cons | O1: C_CEO | P1: C_Ext | Q1: C_CAC | R1: C_Agenc | S1: C_Jur | T1: C_Contab | U1: C_GP | V1: C_Tec | W1: C_Mkt | X1: C_Tel | Y1: C_Desl | Z1: C_Trein | AA1: C_Imp | AB1: C_Com | AC1: Total Custos | AD1: Margem R$ | AE1: Margem %
A2: 2024-01 | B2: Clínica da Cidade | C2: Validação | D2: 9900 | E2: 1 | F2: 9900 | G2: 0 | H2: 7 | I2: 29 | J2: 12 | K2: 0 | L2: 0 | M2: 1087 | N2: 2060 | O2: 833 | P2: 250 | Q2: 0 | R2: 5551 | S2: 0 | T2: 694 | U2: 3000 | V2: 1147 | W2: - | X2: - | Y2: - | Z2: - | AA2: 594 | AB2: 495 | AC2: 15711 | AD2: -5811 | AE2: -0.5869697
A3: 2024-01 | B3: EduKids Brasil | C3: Validação | D3: 9900 | E3: 2 | F3: 19800 | G3: 0 | H3: 17 | I3: 60 | J3: 43 | K3: 0 | L3: 0 | M3: 944 | N3: 3125 | O3: 833 | P3: 250 | Q3: 0 | R3: 6588 | S3: 0 | T3: 347 | U3: 1500 | V3: 996 | W3: - | X3: - | Y3: - | Z3: - | AA3: 1188 | AB3: 990 | AC3: 16761 | AD3: 3039 | AE3: 0.15348485
A4: 2024-02 | B4: Clínica da Cidade | C4: Validação | D4: 9900 | E4: 1 | F4: 9900 | G4: 0 | H4: 8 | I4: 29 | J4: 14 | K4: 0 | L4: 0 | M4: 906 | N4: 2060 | O4: 833 | P4: 250 | Q4: 0 | R4: 5706 | S4: 0 | T4: 694 | U4: 3000 | V4: 955 | W4: - | X4: - | Y4: - | Z4: - | AA4: 594 | AB4: 495 | AC4: 15493 | AD4: -5593 | AE4: -0.56494949
A5: 2024-03 | B5: Cogni Academy | C5: Validação | D5: 9900 | E5: 2 | F5: 19800 | G5: 0 | H5: 16 | I5: 57 | J5: 43 | K5: 0 | L5: 0 | M5: 1018 | N5: 3125 | O5: 833 | P5: 250 | Q5: 0 | R5: 6238 | S5: 0 | T5: 347 | U5: 1500 | V5: 1074 | W5: - | X5: - | Y5: - | Z5: - | AA5: 1188 | AB5: 990 | AC5: 16563 | AD5: 3237 | AE5: 0.16348485
A6: 2024-03 | B6: Clínica da Cidade | C6: Validação | D6: 9900 | E6: 1 | F6: 9900 | G6: 0 | H6: 7 | I6: 33 | J6: 26 | K6: 0 | L6: 0 | M6: 924 | N6: 2344 | O6: 833 | P6: 250 | Q6: 0 | R6: 5797 | S6: 0 | T6: 694 | U6: 3000 | V6: 975 | W6: - | X6: - | Y6: - | Z6: - | AA6: 594 | AB6: 495 | AC6: 15906 | AD6: -6006 | AE6: -0.60666667
A7: 2024-06 | B7: Cogni Academy | C7: Validação | D7: 9900 | E7: 1 | F7: 9900 | G7: 0 | H7: 9 | I7: 32 | J7: 22 | K7: 0 | L7: 0 | M7: 927 | N7: 2273 | O7: 833 | P7: 250 | Q7: 0 | R7: 5711 | S7: 0 | T7: 694 | U7: 3000 | V7: 978 | W7: - | X7: - | Y7: - | Z7: - | AA7: 594 | AB7: 495 | AC7: 15755 | AD7: -5855 | AE7: -0.59141414
A8: 2024-06 | B8: Smart Nutri | C8: Validação | D8: 9900 | E8: 1 | F8: 9900 | G8: 0 | H8: 8 | I8: 32 | J8: 7 | K8: 0 | L8: 0 | M8: 1057 | N8: 2273 | O8: 833 | P8: 250 | Q8: 0 | R8: 5215 | S8: 0 | T8: 694 | U8: 3000 | V8: 1115 | W8: - | X8: - | Y8: - | Z8: - | AA8: 594 | AB8: 495 | AC8: 15526 | AD8: -5626 | AE8: -0.56828283
A9: 2024-06 | B9: EduKids Brasil | C9: Validação | D9: 9900 | E9: 1 | F9: 9900 | G9: 0 | H9: 8 | I9: 33 | J9: 27 | K9: 0 | L9: 0 | M9: 972 | N9: 2344 | O9: 833 | P9: 250 | Q9: 0 | R9: 5289 | S9: 0 | T9: 694 | U9: 3000 | V9: 1026 | W9: - | X9: - | Y9: - | Z9: - | AA9: 594 | AB9: 495 | AC9: 15497 | AD9: -5597 | AE9: -0.56535354
A10: 2024-07 | B10: Cogni Academy | C10: Validação | D10: 9900 | E10: 2 | F10: 19800 | G10: 0 | H10: 17 | I10: 59 | J10: 27 | K10: 0 | L10: 0 | M10: 996 | N10: 3125 | O10: 833 | P10: 250 | Q10: 0 | R10: 6498 | S10: 0 | T10: 347 | U10: 1500 | V10: 1051 | W10: - | X10: - | Y10: - | Z10: - | AA10: 1188 | AB10: 990 | AC10: 16778 | AD10: 3022 | AE10: 0.15262626
A11: 2024-07 | B11: Smart Nutri | C11: Validação | D11: 9900 | E11: 1 | F11: 9900 | G11: 0 | H11: 8 | I11: 31 | J11: 15 | K11: 0 | L11: 0 | M11: 1072 | N11: 2202 | O11: 833 | P11: 250 | Q11: 0 | R11: 5609 | S11: 0 | T11: 694 | U11: 3000 | V11: 1131 | W11: - | X11: - | Y11: - | Z11: - | AA11: 594 | AB11: 495 | AC11: 15880 | AD11: -5980 | AE11: -0.6040404
A12: 2024-07 | B12: EduKids Brasil | C12: Validação | D12: 9900 | E12: 1 | F12: 9900 | G12: 0 | H12: 8 | I12: 30 | J12: 27 | K12: 0 | L12: 0 | M12: 924 | N12: 2131 | O12: 833 | P12: 250 | Q12: 0 | R12: 5499 | S12: 0 | T12: 694 | U12: 3000 | V12: 974 | W12: - | X12: - | Y12: - | Z12: - | AA12: 594 | AB12: 495 | AC12: 15394 | AD12: -5494 | AE12: -0.55494949
A13: 2024-08 | B13: Cogni Academy | C13: Validação | D13: 9900 | E13: 1 | F13: 9900 | G13: 0 | H13: 9 | I13: 31 | J13: 28 | K13: 0 | L13: 0 | M13: 919 | N13: 2202 | O13: 833 | P13: 250 | Q13: 0 | R13: 5869 | S13: 0 | T13: 694 | U13: 3000 | V13: 970 | W13: - | X13: - | Y13: - | Z13: - | AA13: 594 | AB13: 495 | AC13: 15826 | AD13: -5926 | AE13: -0.59858586
... A27: 2024-12 | B27: EduKids Brasil | C27: Validação | D27: 9900 | E27: 1 | F27: 9900 | G27: 0 | H27: 8 | I27: 32 | J27: 7 | K27: 0 | L27: 0 | M27: 1035 | N27: 2273 | O27: 833 | P27: 250 | Q27: 0 | R27: 5818 | S27: 0 | T27: 694 | U27: 3000 | V27: 1092 | W27: - | X27: - | Y27: - | Z27: - | AA27: 594 | AB27: 495 | AC27: 16084 | AD27: -6184 | AE27: -0.62464646

Sheet 4_Base_Regressao
A1: Mês | B1: Franquia | C1: Tipo_Servico | D1: Receita_Total | E1: Qtd_Contratos | F1: H_Total | G1: H_Advogado | H1: Total_Custos | I1: Margem_RS | J1: Margem_PCT | K1: Num_Mes
A2: 2024-01 | B2: Clínica da Cidade | C2: Expansão | D2: 40000 | E2: 4 | F2: 213 | G2: 0 | H2: 12538 | I2: 27462 | J2: 0.68655 | K2: 1
A3: 2024-01 | B3: Cogni Academy | C3: Expansão | D3: 21600 | E3: 4 | F3: 193 | G3: 0 | H3: 10233 | I3: 11367 | J3: 0.52625 | K3: 1
A4: 2024-01 | B4: EduKids Brasil | C4: Expansão | D4: 32000 | E4: 4 | F4: 197 | G4: 0 | H4: 12347 | I4: 19653 | J4: 0.61415625 | K4: 1
A5: 2024-01 | B5: Smart Nutri | C5: Expansão | D5: 40000 | E5: 4 | F5: 192 | G5: 0 | H5: 12247 | I5: 27753 | J5: 0.693825 | K5: 1
A6: 2024-02 | B6: Clínica da Cidade | C6: Expansão | D6: 18000 | E6: 4 | F6: 207 | G6: 0 | H6: 10378 | I6: 7622 | J6: 0.42344444 | K6: 2
A7: 2024-02 | B7: Cogni Academy | C7: Expansão | D7: 32000 | E7: 4 | F7: 205 | G7: 0 | H7: 11567 | I7: 20433 | J7: 0.63853125 | K7: 2
A8: 2024-02 | B8: EduKids Brasil | C8: Expansão | D8: 18000 | E8: 4 | F8: 210 | G8: 0 | H8: 9283 | I8: 8717 | J8: 0.48427778 | K8: 2
A9: 2024-02 | B9: Smart Nutri | C9: Expansão | D9: 12000 | E9: 4 | F9: 213 | G9: 0 | H9: 9732 | I9: 2268 | J9: 0.189 | K9: 2
A10: 2024-03 | B10: Clínica da Cidade | C10: Expansão | D10: 18000 | E10: 4 | F10: 187 | G10: 0 | H10: 9619 | I10: 8381 | J10: 0.46561111 | K10: 3
A11: 2024-03 | B11: Cogni Academy | C11: Expansão | D11: 22500 | E11: 5 | F11: 221 | G11: 0 | H11: 10089 | I11: 12411 | J11: 0.5516 | K11: 3
A12: 2024-03 | B12: EduKids Brasil | C12: Expansão | D12: 12000 | E12: 4 | F12: 211 | G12: 0 | H12: 9911 | I12: 2089 | J12: 0.17408333 | K12: 3
A13: 2024-03 | B13: Smart Nutri | C13: Expansão | D13: 27000 | E13: 5 | F13: 229 | G13: 0 | H13: 11343 | I13: 15657 | J13: 0.57988889 | K13: 3
... A97: 2024-12 | B97: Smart Nutri | C97: Formatação | D97: 103500 | E97: 1 | F97: 104 | G97: 28 | H97: 39262 | I97: 64238 | J97: 0.620657 | K97: 12
A98: 2024-01 | B98: Clínica da Cidade | C98: Validação | D98: 9900 | E98: 1 | F98: 41 | G98: 0 | H98: =Planilha1!AC2 -> 15711 | I98: =Planilha1!AD2 -> -5811 | J98: =Planilha1!AE2 -> -0.5869697 | K98: 1
A99: 2024-01 | B99: EduKids Brasil | C99: Validação | D99: 19800 | E99: 2 | F99: 103 | G99: 0 | H99: =Planilha1!AC3 -> 16761 | I99: =Planilha1!AD3 -> 3039 | J99: =Planilha1!AE3 -> 0.15348485 | K99: 1
A100: 2024-02 | B100: Clínica da Cidade | C100: Validação | D100: 9900 | E100: 1 | F100: 43 | G100: 0 | H100: =Planilha1!AC4 -> 15493 | I100: =Planilha1!AD4 -> -5593 | J100: =Planilha1!AE4 -> -0.56494949 | K100: 2
A101: 2024-03 | B101: Clínica da Cidade | C101: Validação | D101: 9900 | E101: 1 | F101: 100 | G101: 0 | H101: =Planilha1!AC5 -> 16563 | I101: =Planilha1!AD5 -> 3237 | J101: =Planilha1!AE5 -> 0.16348485 | K101: 3
A102: 2024-03 | B102: Cogni Academy | C102: Validação | D102: 19800 | E102: 2 | F102: 59 | G102: 0 | H102: =Planilha1!AC6 -> 15906 | I102: =Planilha1!AD6 -> -6006 | J102: =Planilha1!AE6 -> -0.60666667 | K102: 3
A103: 2024-06 | B103: Cogni Academy | C103: Validação | D103: 9900 | E103: 1 | F103: 54 | G103: 0 | H103: =Planilha1!AC7 -> 15755 | I103: =Planilha1!AD7 -> -5855 | J103: =Planilha1!AE7 -> -0.59141414 | K103: 6
A104: 2024-06 | B104: EduKids Brasil | C104: Validação | D104: 9900 | E104: 1 | F104: 39 | G104: 0 | H104: =Planilha1!AC8 -> 15526 | I104: =Planilha1!AD8 -> -5626 | J104: =Planilha1!AE8 -> -0.56828283 | K104: 6
A105: 2024-06 | B105: Smart Nutri | C105: Validação | D105: 9900 | E105: 1 | F105: 60 | G105: 0 | H105: =Planilha1!AC9 -> 15497 | I105: =Planilha1!AD9 -> -5597 | J105: =Planilha1!AE9 -> -0.56535354 | K105: 6
A106: 2024-07 | B106: Cogni Academy | C106: Validação | D106: 19800 | E106: 2 | F106: 86 | G106: 0 | H106: =Planilha1!AC10 -> 16778 | I106: =Planilha1!AD10 -> 3022 | J106: =Planilha1!AE10 -> 0.15262626 | K106: 7
A107: 2024-07 | B107: EduKids Brasil | C107: Validação | D107: 9900 | E107: 1 | F107: 46 | G107: 0 | H107: =Planilha1!AC11 -> 15880 | I107: =Planilha1!AD11 -> -5980 | J107: =Planilha1!AE11 -> -0.6040404 | K107: 7
A108: 2024-07 | B108: Smart Nutri | C108: Validação | D108: 9900 | E108: 1 | F108: 57 | G108: 0 | H108: =Planilha1!AC12 -> 15394 | I108: =Planilha1!AD12 -> -5494 | J108: =Planilha1!AE12 -> -0.55494949 | K108: 7
A109: 2024-08 | B109: Clínica da Cidade | C109: Validação | D109: 9900 | E109: 1 | F109: 59 | G109: 0 | H109: =Planilha1!AC13 -> 15826 | I109: =Planilha1!AD13 -> -5926 | J109: =Planilha1!AE13 -> -0.59858586 | K109: 8
... A123: 2024-12 | B123: Smart Nutri | C123: Validação | D123: 9900 | E123: 1 | F123: 39 | G123: 0 | H123: =Planilha1!AC27 -> 16084 | I123: =Planilha1!AD27 -> -6184 | J123: =Planilha1!AE27 -> -0.62464646 | K123: 12

Sheet Planilha2
A1: RESUMO DOS RESULTADOS
A3: Estatística de regressão
A4: R múltiplo | B4: 0.53498768
A5: R-Quadrado | B5: 0.28621182
A6: R-quadrado ajustado | B6: 0.22414328
A7: Erro padrão | B7: 561.70981
A8: Observações | B8: 26
A10: ANOVA
B11: gl | C11: SQ | D11: MQ | E11: F | F11: F de significação
A12: Regressão | B12: 2 | C12: 2909846.4 | D12: 1454923.2 | E12: 4.6112223 | F12: 0.02070368
A13: Resíduo | B13: 23 | C13: 7256911.9 | D13: 315517.91
A14: Total | B14: 25 | C14: 10166758
B16: Coeficientes | C16: Erro padrão | D16: Stat t | E16: valor-P | F16: 95% inferiores | G16: 95% superiores | H16: Inferior 90,0% | I16: Superior 90,0%
A17: Interseção | B17: 8962.6753 | C17: 364.13393 | D17: 24.613678 | E17: 5.0176891e-18 | F17: 8209.4068 | G17: 9715.9437 | H17: 8338.5965 | I17: 9586.754
A18: QTD_Contratos | B18: -753.44876 | C18: 1737.1296 | D18: -0.43373205 | E18: 0.6685242 | F18: -4346.9751 | G18: 2840.0775 | H18: -3730.6657 | I18: 2223.7682
A19: H_total | B19: 53.936615 | C19: 59.159352 | D19: 0.91171748 | E19: 0.37137491 | F19: -68.443828 | G19: 176.31706 | H19: -47.454914 | I19: 155.32814
A23: RESULTADOS DE RESÍDUOS
A25: Observação | B25: Previsto(a) Tot_Custos | C25: Resíduos | D25: Resíduos padrão
A26: 1 | B26: 9773.3883 | C26: -173.38834 | D26: -0.32182069
A27: 2 | B27: 10691.975 | C27: -443.97465 | D27: -0.8240475
A28: 3 | B28: 9773.3883 | C28: -638.38834 | D28: -1.1848927
A29: 4 | B29: 10530.165 | C29: -76.1648 | D29: -0.14136711
A30: 5 | B30: 9989.1348 | C30: -597.1348 | D30: -1.1083233
A31: 6 | B31: 9935.1982 | C31: -567.19818 | D31: -1.0527589
A32: 7 | B32: 9935.1982 | C32: 1163.8018 | D32: 2.1600963
A33: 8 | B33: 9989.1348 | C33: 704.8652 | D33: 1.3082783
A34: 9 | B34: 10638.038 | C34: 542.96197 | D34: 1.0077748
A35: 10 | B35: 9881.2616 | C35: 759.73843 | D35: 1.4101268
A36: 11 | B36: 9827.325 | C36: -400.32495 | D36: -0.74303067
A37: 12 | B37: 9881.2616 | C37: -264.26157 | D37: -0.49048766
... A51: 26 | B51: 9935.1982 | C51: 46.801817 | D51: 0.086867394

Sheet Planilha11
A1: RESUMO DOS RESULTADOS
A3: Estatística de regressão
A4: R múltiplo | B4: 0.68019971
A5: R-Quadrado | B5: 0.46267165
A6: R-quadrado ajustado | B6: 0.43708458
A7: Erro padrão | B7: 436.82917
A8: Observações | B8: 23
A10: ANOVA
B11: gl | C11: SQ | D11: MQ | E11: F | F11: F de significação
A12: Regressão | B12: 1 | C12: 3450449.6 | D12: 3450449.6 | E12: 18.082248 | F12: 0.00035539037
A13: Resíduo | B13: 21 | C13: 4007214.3 | D13: 190819.73
A14: Total | B14: 22 | C14: 7457663.9
B16: Coeficientes | C16: Erro padrão | D16: Stat t | E16: valor-P | F16: 95% inferiores | G16: 95% superiores | H16: Inferior 90,0% | I16: Superior 90,0%
A17: Interseção | B17: 8865.9661 | C17: 259.93669 | D17: 34.108175 | E17: 7.0941598e-20 | F17: 8325.3982 | G17: 9406.534 | H17: 8418.6819 | I17: 9313.2503
A18: Tot_horas | B18: 14.725281 | C18: 3.4628795 | D18: 4.2523227 | E18: 0.00035539037 | F18: 7.5238289 | G18: 21.926733 | H18: 8.7665558 | I18: 20.684007
A22: RESULTADOS DE RESÍDUOS
A24: Observação | B24: Previsto(a) Total Custos | C24: Resíduos | D24: Resíduos padrão
A25: 1 | B25: 9572.7796 | C25: 27.220401 | D25: 0.06378001
A26: 2 | B26: 10633 | C26: -384.99984 | D26: -0.90209154
A27: 3 | B27: 9616.9554 | C27: -481.95544 | D27: -1.1292678
A28: 4 | B28: 10574.099 | C28: -120.09872 | D28: -0.28140281
A29: 5 | B29: 9837.8347 | C29: -445.83466 | D29: -1.0446333
A30: 6 | B30: 9793.6588 | C30: -425.65882 | D30: -0.99735941
A31: 7 | B31: 9867.2852 | C31: 826.71478 | D31: 1.937072
A32: 8 | B32: 10382.67 | C32: 798.32994 | D32: 1.8705636
A33: 9 | B33: 9661.1313 | C33: 979.86871 | D33: 2.2959263
A34: 10 | B34: 9823.1094 | C34: -396.10938 | D34: -0.92812225
A35: 11 | B35: 9867.2852 | C35: -250.28522 | D35: -0.58644227
A36: 12 | B36: 9631.6807 | C36: 266.31928 | D36: 0.6240116
... A47: 23 | B47: 9558.0543 | C47: 423.94568 | D47: 0.99334538

Sheet Planilha17
A1: RESUMO DOS RESULTADOS
A3: Estatística de regressão
A4: R múltiplo | B4: 0.69076629
A5: R-Quadrado | B5: 0.47715807
A6: R-quadrado ajustado | B6: 0.39460408
A7: Erro padrão | B7: 477.71836
A8: Observações | B8: 23
A10: ANOVA
B11: gl | C11: SQ | D11: MQ | E11: F | F11: F de significação
A12: Regressão | B12: 3 | C12: 3957212.1 | D12: 1319070.7 | E12: 5.7799518 | F12: 0.0055323145
A13: Resíduo | B13: 19 | C13: 4336081.7 | D13: 228214.83
A14: Total | B14: 22 | C14: 8293293.8
B16: Coeficientes | C16: Erro padrão | D16: Stat t | E16: valor-P | F16: 95% inferiores | G16: 95% superiores | H16: Inferior 90,0% | I16: Superior 90,0%
A17: Interseção | B17: 8586.1967 | C17: 345.18724 | D17: 24.874027 | E17: 5.8476089e-16 | F17: 7863.7115 | G17: 9308.6819 | H17: 7989.3221 | I17: 9183.0713
A18: H_Cons | B18: 74.789953 | C18: 36.082073 | D18: 2.0727731 | E18: 0.052039414 | F18: -0.73069495 | G18: 150.3106 | H18: 12.399256 | I18: 137.18065
A19: H_GP | B19: -2.0799145 | C19: 12.75216 | D19: -0.16310291 | E19: 0.87215972 | F19: -28.770493 | G19: 24.610664 | H19: -24.130094 | I19: 19.970265
A20: H_Vend | B20: -138.03376 | C20: 121.83819 | D20: -1.1329269 | E20: 0.27133961 | F20: -393.04402 | G20: 116.9765 | H20: -348.70817 | I20: 72.640652
A24: RESULTADOS DE RESÍDUOS
A26: Observação | B26: Previsto(a) Total Custos | C26: Resíduos | D26: Resíduos padrão
A27: 1 | B27: 9763.9101 | C27: -163.91005 | D27: -0.36920553
A28: 2 | B28: 10637.584 | C28: -389.58366 | D28: -0.87753276
A29: 3 | B29: 9621.7165 | C29: -486.71647 | D29: -1.0963233
A30: 4 | B30: 10551.248 | C30: -97.247555 | D30: -0.21904901
A31: 5 | B31: 10033.951 | C31: -641.95106 | D31: -1.4459875
A32: 6 | B32: 9691.4132 | C32: -323.41325 | D32: -0.72848467
A33: 7 | B33: 9893.8374 | C33: 800.16261 | D33: 1.8023572
A34: 8 | B34: 10596.072 | C34: 584.92767 | D34: 1.3175429
A35: 9 | B35: 9769.2165 | C35: 871.78354 | D35: 1.9636825
A36: 10 | B36: 9669.4675 | C36: -242.46753 | D36: -0.54615536
A37: 11 | B37: 9604.1438 | C37: 12.85619 | D37: 0.028958421
A38: 12 | B38: 9542.7667 | C38: 355.23332 | D38: 0.80015901
... A49: 23 | B49: 9860.6457 | C49: 121.35427 | D49: 0.27334913
J56: Qtd | K56: C_Agenc | N56: Qtd | O56: C_Agenc
I57: =J57=N57 -> TRUE | J57: 4 | K57: 8451 | N57: 4 | O57: 8501
I58: =J58=N58 -> TRUE | J58: 1 | K58: 5417 | N58: 1 | O58: 5102
I59: =J59=N59 -> TRUE | J59: 4 | K59: 8383 | N59: 4 | O59: 8933
I60: =J60=N60 -> TRUE | J60: 1 | K60: 5938 | N60: 1 | O60: 5450
I61: =J61=N61 -> TRUE | J61: 1 | K61: 5551 | N61: 1 | O61: 5200
I62: =J62=N62 -> TRUE | J62: 4 | K62: 8815 | N62: 4 | O62: 8111
I63: =J63=N63 -> TRUE | J63: 1 | K63: 5903 | N63: 1 | O63: 5888
I64: =J64=N64 -> TRUE | J64: 4 | K64: 8055 | N64: 4 | O64: 8222
I65: =J65=N65 -> TRUE | J65: 1 | K65: 5445 | N65: 1 | O65: 5999
I66: =J66=N66 -> TRUE | J66: 2 | K66: 6588 | N66: 2 | O66: 6500
I67: =J67=N67 -> TRUE | J67: 4 | K67: 8460 | N67: 4 | O67: 8765
I68: =J68=N68 -> TRUE | J68: 1 | K68: 5224 | N68: 1 | O68: 5321
... I178: =J178=N178 -> TRUE | J178: 1 | K178: 5818 | N178: 1 | O178: 5350
I179: =J179=N179 -> FALSE | N179: 1 | O179: 5960

Sheet REG_VAL
A1: QTD_Contratos | B1: H_total | C1: Tot_Custos | D1: Margem_R$ | E1: Margem_PCT | F1: NUM_MÊS
A2: 1 | B2: 29 | C2: 9600 | D2: 300 | E2: 0.0303 | F2: 1
A3: 2 | B3: 60 | C3: 10248 | D3: 9552 | E3: 0.4824 | F3: 1
A4: 1 | B4: 29 | C4: 9135 | D4: 765 | E4: 0.0773 | F4: 2
A5: 2 | B5: 57 | C5: 10454 | D5: 9346 | E5: 0.472 | F5: 3
A6: 1 | B6: 33 | C6: 9392 | D6: 508 | E6: 0.0513 | F6: 3
A7: 1 | B7: 32 | C7: 9368 | D7: 532 | E7: 0.0537 | F7: 6
A8: 1 | B8: 32 | C8: 11099 | D8: -1199 | E8: -0.1211 | F8: 6
A9: 1 | B9: 33 | C9: 10694 | D9: -794 | E9: -0.0802 | F9: 6
A10: 2 | B10: 59 | C10: 11181 | D10: 8619 | E10: 0.4353 | F10: 7
A11: 1 | B11: 31 | C11: 10641 | D11: -741 | E11: -0.0748 | F11: 7
A12: 1 | B12: 30 | C12: 9427 | D12: 473 | E12: 0.0478 | F12: 7
A13: 1 | B13: 31 | C13: 9617 | D13: 283 | E13: 0.0286 | F13: 8
... A27: 1 | B27: 32 | C27: 9982 | D27: -82 | E27: -0.0083 | F27: 12
A33: NUM_MÊS | B33: Qtd | C33: H_Cons | D33: H_GP | E33: H_Vend | F33: Total Custos | G33: C_Vend | H33: C_Cons | I33: C_Agenc | J33: C_GP | K33: C_Tec | L33: C_Imp | M33: C_Com | N33: Total Custos | O33: Margem R$ | P33: Margem %
A34: 1 | B34: 1 | C34: 29 | D34: 12 | E34: 7 | F34: 9600 | G34: 1087 | H34: 2060 | I34: 1217 | J34: 3000 | K34: 1147 | L34: 594 | M34: 495 | N34: 9600 | O34: 300 | P34: 0.0303
A35: 1 | B35: 2 | C35: 60 | D35: 43 | E35: 17 | F35: 10248 | G35: 944 | H35: 3125 | I35: 1505 | J35: 1500 | K35: 996 | L35: 1188 | M35: 990 | N35: 10248 | O35: 9552 | P35: 0.4824
A36: 2 | B36: 1 | C36: 29 | D36: 14 | E36: 8 | F36: 9135 | G36: 906 | H36: 2060 | I36: 1125 | J36: 3000 | K36: 955 | L36: 594 | M36: 495 | N36: 9135 | O36: 765 | P36: 0.0773
A37: 3 | B37: 2 | C37: 57 | D37: 43 | E37: 16 | F37: 10454 | G37: 1018 | H37: 3125 | I37: 1559 | J37: 1500 | K37: 1074 | L37: 1188 | M37: 990 | N37: 10454 | O37: 9346 | P37: 0.472
A38: 3 | B38: 1 | C38: 33 | D38: 26 | E38: 7 | F38: 9392 | G38: 924 | H38: 2344 | I38: 1060 | J38: 3000 | K38: 975 | L38: 594 | M38: 495 | N38: 9392 | O38: 508 | P38: 0.0513
A39: 6 | B39: 1 | C39: 32 | D39: 22 | E39: 9 | F39: 9368 | G39: 927 | H39: 2273 | I39: 1101 | J39: 3000 | K39: 978 | L39: 594 | M39: 495 | N39: 9368 | O39: 532 | P39: 0.0537
A40: 6 | B40: 1 | C40: 33 | D40: 27 | E40: 8 | F40: 10694 | G40: 972 | H40: 2344 | I40: 2263 | J40: 3000 | K40: 1026 | L40: 594 | M40: 495 | N40: 10694 | O40: -794 | P40: -0.0802
A41: 7 | B41: 2 | C41: 59 | D41: 27 | E41: 17 | F41: 11181 | G41: 996 | H41: 3125 | I41: 2331 | J41: 1500 | K41: 1051 | L41: 1188 | M41: 990 | N41: 11181 | O41: 8619 | P41: 0.4353
A42: 7 | B42: 1 | C42: 31 | D42: 15 | E42: 8 | F42: 10641 | G42: 1072 | H42: 2202 | I42: 2147 | J42: 3000 | K42: 1131 | L42: 594 | M42: 495 | N42: 10641 | O42: -741 | P42: -0.0748
A43: 7 | B43: 1 | C43: 30 | D43: 27 | E43: 8 | F43: 9427 | G43: 924 | H43: 2131 | I43: 1309 | J43: 3000 | K43: 974 | L43: 594 | M43: 495 | N43: 9427 | O43: 473 | P43: 0.0478
A44: 8 | B44: 1 | C44: 31 | D44: 28 | E44: 9 | F44: 9617 | G44: 919 | H44: 2202 | I44: 1437 | J44: 3000 | K44: 970 | L44: 594 | M44: 495 | N44: 9617 | O44: 283 | P44: 0.0286
A45: 8 | B45: 1 | C45: 28 | D45: 16 | E45: 8 | F45: 9898 | G45: 1008 | H45: 1989 | I45: 1749 | J45: 3000 | K45: 1063 | L45: 594 | M45: 495 | N45: 9898 | O45: 2 | P45: 0.0002
... A56: 12 | B56: 1 | C56: 32 | D56: 7 | E56: 8 | F56: 9982 | G56: 1035 | H56: 2273 | I56: 1493 | J56: 3000 | K56: 1092 | L56: 594 | M56: 495 | N56: 9982 | O56: -82 | P56: -0.0083
N57: =AVERAGE(O34:O56) -> 2106.2609 | O57: =AVERAGE(P34:P56) -> 0.11251739
A66: NUM_MÊS | B66: Qtd | C66: H_Cons | D66: H_GP | E66: H_Vend | F66: Total Custos | G66: C_Vend | H66: C_Cons | I66: C_Agenc | J66: C_GP | K66: C_Tec | L66: C_Imp | M66: C_Com | N66: Total Custos | O66: Margem R$ | P66: Margem %
A67: 1 | B67: 1 | C67: 29 | D67: 12 | E67: 7 | F67: 9600 | G67: 1087 | H67: 2060 | I67: 1217 | J67: 3000 | K67: 1147 | L67: 594 | M67: 495 | N67: =SUM(G67:M67) -> 9600 | O67: 300 | P67: 0.0303
A68: 1 | B68: 2 | C68: 60 | D68: 43 | E68: 17 | F68: 10248 | G68: 944 | H68: 3125 | I68: 1505 | J68: 1500 | K68: 996 | L68: 1188 | M68: 990 | N68: =SUM(G68:M68) -> 10248 | O68: 9552 | P68: 0.4824
A69: 2 | B69: 1 | C69: 29 | D69: 14 | E69: 8 | F69: 9135 | G69: 906 | H69: 2060 | I69: 1125 | J69: 3000 | K69: 955 | L69: 594 | M69: 495 | N69: =SUM(G69:M69) -> 9135 | O69: 765 | P69: 0.0773
A70: 3 | B70: 2 | C70: 57 | D70: 43 | E70: 16 | F70: 10454 | G70: 1018 | H70: 3125 | I70: 1559 | J70: 1500 | K70: 1074 | L70: 1188 | M70: 990 | N70: =SUM(G70:M70) -> 10454 | O70: 9346 | P70: 0.472
A71: 3 | B71: 1 | C71: 33 | D71: 26 | E71: 7 | F71: 9392 | G71: 924 | H71: 2344 | I71: 1060 | J71: 3000 | K71: 975 | L71: 594 | M71: 495 | N71: =SUM(G71:M71) -> 9392 | O71: 508 | P71: 0.0513
A72: 6 | B72: 1 | C72: 32 | D72: 22 | E72: 9 | F72: 9368 | G72: 927 | H72: 2273 | I72: 1101 | J72: 3000 | K72: 978 | L72: 594 | M72: 495 | N72: =SUM(G72:M72) -> 9368 | O72: 532 | P72: 0.0537
A73: 6 | B73: 1 | C73: 32 | D73: 7 | E73: 8 | F73: 11099 | G73: 1057 | H73: 2273 | I73: 2565 | J73: 3000 | K73: 1115 | L73: 594 | M73: 495 | N73: =SUM(G73:M73) -> 11099 | O73: -1199 | P73: -0.1211
A74: 6 | B74: 1 | C74: 33 | D74: 27 | E74: 8 | F74: 10694 | G74: 972 | H74: 2344 | I74: 2263 | J74: 3000 | K74: 1026 | L74: 594 | M74: 495 | N74: =SUM(G74:M74) -> 10694 | O74: -794 | P74: -0.0802
A75: 7 | B75: 2 | C75: 59 | D75: 27 | E75: 17 | F75: 11181 | G75: 996 | H75: 3125 | I75: 2331 | J75: 1500 | K75: 1051 | L75: 1188 | M75: 990 | N75: =SUM(G75:M75) -> 11181 | O75: 8619 | P75: 0.4353
A76: 7 | B76: 1 | C76: 31 | D76: 15 | E76: 8 | F76: 10641 | G76: 1072 | H76: 2202 | I76: 2147 | J76: 3000 | K76: 1131 | L76: 594 | M76: 495 | N76: =SUM(G76:M76) -> 10641 | O76: -741 | P76: -0.0748
A77: 7 | B77: 1 | C77: 30 | D77: 27 | E77: 8 | F77: 9427 | G77: 924 | H77: 2131 | I77: 1309 | J77: 3000 | K77: 974 | L77: 594 | M77: 495 | N77: =SUM(G77:M77) -> 9427 | O77: 473 | P77: 0.0478
A78: 8 | B78: 1 | C78: 31 | D78: 28 | E78: 9 | F78: 9617 | G78: 919 | H78: 2202 | I78: 1437 | J78: 3000 | K78: 970 | L78: 594 | M78: 495 | N78: =SUM(G78:M78) -> 9617 | O78: 283 | P78: 0.0286
... A92: 12 | B92: 1 | C92: 32 | D92: 7 | E92: 8 | F92: 9982 | G92: 1035 | H92: 2273 | I92: 1493 | J92: 3000 | K92: 1092 | L92: 594 | M92: 495 | N92: =SUM(G92:M92) -> 9982 | O92: -82 | P92: -0.0083
D96: =SUM(C67:D67) -> 41
D97: =SUM(C68:D68) -> 103
D98: =SUM(C69:D69) -> 43
D99: =SUM(C70:D70) -> 100
D100: =SUM(C71:D71) -> 59
D101: =SUM(C72:D72) -> 54
D102: =SUM(C73:D73) -> 39
D103: =SUM(C74:D74) -> 60
D104: =SUM(C75:D75) -> 86
D105: =SUM(C76:D76) -> 46
D106: =SUM(C77:D77) -> 57
D107: =SUM(C78:D78) -> 59
... D121: =SUM(C92:D92) -> 39
